{"generated_at":"2026-07-11T18:10:16Z","newest_granule":"2026-07-11T18:06:18Z","product":"GOES-R ABI L2 FDC (Fire/Hot Spot Characterization), CONUS sector, 2km","counts":{"total":20,"g19":9,"g18":14},"detections":[{"lat":35.802,"lng":-114.9582,"tier":"good","sat":"G18","age_sec":238,"frp":1337.9,"tempK":1471.2},{"lat":35.6105,"lng":-115.3555,"tier":"good","sat":"G18","age_sec":238,"frp":507.2,"tempK":882.3},{"lat":35.6369,"lng":-115.3213,"tier":"good","sat":"G18","age_sec":238,"frp":437.0,"tempK":1199.4},{"lat":35.8009,"lng":-114.9843,"tier":"good","sat":"G18","age_sec":238,"frp":392.2,"tempK":1242.1},{"lat":50.2028,"lng":-79.1145,"tier":"good","sat":"G19","age_sec":239,"frp":333.7,"tempK":649.0},{"lat":50.2025,"lng":-79.0843,"tier":"good","sat":"G19","age_sec":239,"frp":274.1,"tempK":493.3},{"lat":35.803,"lng":-114.9322,"tier":"good","sat":"G18","age_sec":238,"frp":199.5,"tempK":658.5},{"lat":35.6013,"lng":-119.8583,"tier":"good","sat":"G18","age_sec":238,"frp":166.8,"tempK":464.2},{"lat":38.1457,"lng":-107.3727,"tier":"good","sat":"G19","age_sec":239,"frp":153.3,"tempK":896.0},{"lat":35.6095,"lng":-115.3814,"tier":"good","sat":"G18","age_sec":238,"frp":130.5,"tempK":441.7},{"lat":35.8275,"lng":-114.9495,"tier":"good","sat":"G18","age_sec":238,"frp":119.5,"tempK":465.7},{"lat":28.9078,"lng":-81.3103,"tier":"good","sat":"G19","age_sec":239,"frp":68.2,"tempK":401.4},{"lat":34.4581,"lng":-96.9775,"tier":"high","sat":"G19","age_sec":239,"frp":63.2},{"lat":37.7773,"lng":-105.5286,"tier":"good","sat":"G18","age_sec":238,"frp":62.0,"tempK":436.2},{"lat":19.0424,"lng":-71.5986,"tier":"good","sat":"G19","age_sec":239,"frp":55.2,"tempK":602.8},{"lat":33.4375,"lng":-110.8467,"tier":"good","sat":"G18","age_sec":238,"frp":53.7,"tempK":404.5},{"lat":33.4209,"lng":-110.8617,"tier":"good","sat":"G19","age_sec":239,"frp":50.4,"tempK":407.2},{"lat":17.9403,"lng":-71.3179,"tier":"good","sat":"G19","age_sec":239,"frp":49.3,"tempK":461.1},{"lat":17.9207,"lng":-71.3184,"tier":"good","sat":"G19","age_sec":239,"frp":46.6,"tempK":458.6},{"lat":33.2505,"lng":-115.5003,"tier":"good","sat":"G18","age_sec":238,"frp":39.4,"tempK":423.4}]}