{"generated_at":"2026-07-01T00:35:10Z","newest_granule":"2026-07-01T00:31:23Z","product":"GOES-R ABI L2 FDC (Fire/Hot Spot Characterization), CONUS sector, 2km","counts":{"total":55,"g19":25,"g18":36},"detections":[{"lat":37.7424,"lng":-109.8095,"tier":"good","sat":"G19","age_sec":233,"frp":2760.9,"tempK":781.7},{"lat":38.1337,"lng":-107.5995,"tier":"good","sat":"G18","age_sec":227,"frp":2050.9,"tempK":897.9},{"lat":38.1608,"lng":-107.5854,"tier":"high","sat":"G18","age_sec":227,"frp":1844.4},{"lat":37.7554,"lng":-109.7816,"tier":"good","sat":"G18","age_sec":227,"frp":1622.0,"tempK":756.5},{"lat":38.1882,"lng":-107.641,"tier":"high","sat":"G19","age_sec":233,"frp":1533.9},{"lat":37.7403,"lng":-109.7768,"tier":"good","sat":"G19","age_sec":233,"frp":911.1,"tempK":2637.9},{"lat":38.188,"lng":-107.5713,"tier":"high","sat":"G18","age_sec":227,"frp":762.1},{"lat":38.1575,"lng":-107.6452,"tier":"good","sat":"G18","age_sec":227,"frp":761.8,"tempK":814.6},{"lat":38.1608,"lng":-107.6248,"tier":"high","sat":"G19","age_sec":233,"frp":745.8},{"lat":38.1901,"lng":-107.6726,"tier":"high","sat":"G19","age_sec":233,"frp":673.6},{"lat":38.1049,"lng":-107.6433,"tier":"high","sat":"G18","age_sec":227,"frp":637.9},{"lat":38.1372,"lng":-107.6717,"tier":"high","sat":"G19","age_sec":233,"frp":619.6},{"lat":37.7583,"lng":-109.7242,"tier":"high","sat":"G18","age_sec":227,"frp":602.3},{"lat":38.1646,"lng":-107.6879,"tier":"high","sat":"G19","age_sec":233,"frp":582.5},{"lat":37.9434,"lng":-109.6938,"tier":"good","sat":"G18","age_sec":227,"frp":533.5,"tempK":750.2},{"lat":34.9852,"lng":-111.8243,"tier":"good","sat":"G18","age_sec":227,"frp":477.5,"tempK":909.3},{"lat":38.1863,"lng":-107.6094,"tier":"high","sat":"G19","age_sec":233,"frp":468.6},{"lat":34.984,"lng":-111.851,"tier":"high","sat":"G18","age_sec":227,"frp":370.9},{"lat":38.1065,"lng":-107.6135,"tier":"high","sat":"G18","age_sec":227,"frp":350.1},{"lat":34.9831,"lng":-111.8905,"tier":"high","sat":"G19","age_sec":233,"frp":344.6},{"lat":37.83,"lng":-109.8592,"tier":"good","sat":"G18","age_sec":227,"frp":316.4,"tempK":558.7},{"lat":35.0092,"lng":-111.8413,"tier":"high","sat":"G18","age_sec":227,"frp":312.4},{"lat":37.9105,"lng":-109.8217,"tier":"good","sat":"G18","age_sec":227,"frp":296.1,"tempK":1086.9},{"lat":38.1624,"lng":-107.5555,"tier":"high","sat":"G18","age_sec":227,"frp":292.6},{"lat":34.96,"lng":-111.8339,"tier":"good","sat":"G18","age_sec":227,"frp":285.9,"tempK":1392.9},{"lat":38.192,"lng":-107.7042,"tier":"high","sat":"G19","age_sec":233,"frp":260.2},{"lat":34.9612,"lng":-111.8072,"tier":"good","sat":"G18","age_sec":227,"frp":252.6,"tempK":763.2},{"lat":37.7542,"lng":-108.7284,"tier":"good","sat":"G19","age_sec":233,"frp":247.9,"tempK":569.8},{"lat":37.7619,"lng":-108.6487,"tier":"good","sat":"G18","age_sec":227,"frp":239.2,"tempK":1768.1},{"lat":37.7366,"lng":-108.6326,"tier":"good","sat":"G18","age_sec":227,"frp":226.4,"tempK":1100.0},{"lat":37.7603,"lng":-108.6779,"tier":"high","sat":"G18","age_sec":227,"frp":214.6},{"lat":38.3594,"lng":-112.4791,"tier":"good","sat":"G18","age_sec":227,"frp":207.2,"tempK":498.2},{"lat":37.735,"lng":-108.6618,"tier":"good","sat":"G18","age_sec":227,"frp":196.8,"tempK":820.8},{"lat":38.1896,"lng":-107.5414,"tier":"high","sat":"G18","age_sec":227,"frp":196.2},{"lat":37.8394,"lng":-109.6829,"tier":"high","sat":"G19","age_sec":233,"frp":189.0},{"lat":37.8836,"lng":-109.8342,"tier":"high","sat":"G18","age_sec":227,"frp":178.7},{"lat":19.406,"lng":-155.2821,"tier":"high","sat":"G18","age_sec":227,"frp":174.0},{"lat":37.7334,"lng":-108.691,"tier":"good","sat":"G18","age_sec":227,"frp":173.6,"tempK":610.2},{"lat":35.009,"lng":-111.9067,"tier":"high","sat":"G19","age_sec":233,"frp":172.5},{"lat":37.8553,"lng":-109.8754,"tier":"good","sat":"G18","age_sec":227,"frp":163.6,"tempK":1060.3},{"lat":38.3864,"lng":-112.4677,"tier":"good","sat":"G18","age_sec":227,"frp":160.4,"tempK":604.3},{"lat":37.9478,"lng":-109.6072,"tier":"good","sat":"G18","age_sec":227,"frp":158.4,"tempK":563.7},{"lat":37.6561,"lng":-108.6718,"tier":"good","sat":"G18","age_sec":227,"frp":147.7,"tempK":551.1},{"lat":38.3581,"lng":-112.507,"tier":"good","sat":"G18","age_sec":227,"frp":147.5,"tempK":508.9},{"lat":17.8343,"lng":-93.1151,"tier":"good","sat":"G19","age_sec":233,"frp":110.2,"tempK":520.4},{"lat":49.3922,"lng":-113.4947,"tier":"high","sat":"G19","age_sec":233,"frp":90.2},{"lat":17.8946,"lng":-93.1848,"tier":"high","sat":"G19","age_sec":233,"frp":68.9},{"lat":18.6375,"lng":-69.3703,"tier":"high","sat":"G19","age_sec":233,"frp":64.2},{"lat":43.7306,"lng":-107.2119,"tier":"medium","sat":"G19","age_sec":233,"frp":54.7},{"lat":33.0479,"lng":-80.7223,"tier":"good","sat":"G19","age_sec":233,"frp":50.4,"tempK":825.8},{"lat":37.4216,"lng":-94.0033,"tier":"good","sat":"G19","age_sec":233,"frp":43.8,"tempK":799.7},{"lat":41.3246,"lng":-99.8832,"tier":"good","sat":"G19","age_sec":233,"frp":35.3,"tempK":562.9},{"lat":22.699,"lng":-79.8939,"tier":"good","sat":"G19","age_sec":233,"frp":32.8,"tempK":629.9},{"lat":22.6362,"lng":-79.6922,"tier":"good","sat":"G19","age_sec":233,"frp":30.8,"tempK":685.5},{"lat":26.4502,"lng":-100.1557,"tier":"good","sat":"G19","age_sec":233,"frp":25.6,"tempK":482.9}]}