{"generated_at":"2026-07-11T22:43:31Z","newest_granule":"2026-07-11T22:36:18Z","product":"GOES-R ABI L2 FDC (Fire/Hot Spot Characterization), CONUS sector, 2km","counts":{"total":38,"g19":25,"g18":19},"detections":[{"lat":40.1548,"lng":-112.5747,"tier":"good","sat":"G19","age_sec":434,"frp":3397.9,"tempK":1079.6},{"lat":40.1839,"lng":-112.597,"tier":"high","sat":"G19","age_sec":434,"frp":1915.7},{"lat":45.0123,"lng":-118.1541,"tier":"good","sat":"G18","age_sec":433,"frp":1066.5,"tempK":969.0},{"lat":45.0044,"lng":-118.2098,"tier":"high","sat":"G19","age_sec":434,"frp":1038.8},{"lat":45.0345,"lng":-118.2018,"tier":"high","sat":"G19","age_sec":434,"frp":741.5},{"lat":44.8158,"lng":-118.4322,"tier":"good","sat":"G18","age_sec":433,"frp":631.8,"tempK":769.9},{"lat":40.1864,"lng":-112.6333,"tier":"high","sat":"G19","age_sec":434,"frp":614.3},{"lat":40.0618,"lng":-121.1268,"tier":"good","sat":"G19","age_sec":434,"frp":534.1,"tempK":632.4},{"lat":40.0317,"lng":-121.0949,"tier":"good","sat":"G19","age_sec":434,"frp":530.0,"tempK":678.3},{"lat":44.7858,"lng":-118.4147,"tier":"high","sat":"G18","age_sec":433,"frp":455.2},{"lat":40.0313,"lng":-121.0516,"tier":"good","sat":"G18","age_sec":433,"frp":433.9,"tempK":536.9},{"lat":40.1523,"lng":-112.5387,"tier":"high","sat":"G19","age_sec":434,"frp":428.2},{"lat":39.7069,"lng":-120.1543,"tier":"good","sat":"G18","age_sec":433,"frp":414.1,"tempK":691.1},{"lat":40.058,"lng":-121.0703,"tier":"good","sat":"G18","age_sec":433,"frp":389.9,"tempK":667.5},{"lat":45.0005,"lng":-118.1641,"tier":"high","sat":"G19","age_sec":434,"frp":378.6},{"lat":44.7523,"lng":-118.4851,"tier":"high","sat":"G18","age_sec":433,"frp":354.5},{"lat":42.6196,"lng":-122.9701,"tier":"good","sat":"G18","age_sec":433,"frp":324.0,"tempK":531.2},{"lat":40.1813,"lng":-112.561,"tier":"high","sat":"G19","age_sec":434,"frp":312.2},{"lat":44.7816,"lng":-118.46,"tier":"high","sat":"G19","age_sec":434,"frp":284.1},{"lat":44.7211,"lng":-118.4969,"tier":"good","sat":"G18","age_sec":433,"frp":273.0,"tempK":451.1},{"lat":44.8171,"lng":-118.4029,"tier":"high","sat":"G18","age_sec":433,"frp":262.4},{"lat":39.7059,"lng":-120.1806,"tier":"good","sat":"G18","age_sec":433,"frp":257.3,"tempK":411.4},{"lat":49.5305,"lng":-79.4379,"tier":"good","sat":"G19","age_sec":434,"frp":256.7,"tempK":572.1},{"lat":42.6187,"lng":-122.9971,"tier":"good","sat":"G18","age_sec":433,"frp":237.5,"tempK":540.6},{"lat":37.8652,"lng":-108.8273,"tier":"high","sat":"G19","age_sec":434,"frp":218.4},{"lat":40.1332,"lng":-112.5751,"tier":"high","sat":"G18","age_sec":433,"frp":215.1},{"lat":44.7535,"lng":-118.4558,"tier":"high","sat":"G18","age_sec":433,"frp":187.5},{"lat":42.6489,"lng":-122.9624,"tier":"high","sat":"G18","age_sec":433,"frp":162.7},{"lat":33.3209,"lng":-112.8945,"tier":"good","sat":"G19","age_sec":434,"frp":100.3,"tempK":983.2},{"lat":33.3228,"lng":-112.927,"tier":"good","sat":"G19","age_sec":434,"frp":86.7,"tempK":579.0},{"lat":20.9963,"lng":-76.7883,"tier":"good","sat":"G19","age_sec":434,"frp":73.0,"tempK":600.5},{"lat":33.3732,"lng":-112.9582,"tier":"good","sat":"G19","age_sec":434,"frp":69.4,"tempK":835.2},{"lat":33.3713,"lng":-112.9256,"tier":"good","sat":"G19","age_sec":434,"frp":68.7,"tempK":580.5},{"lat":34.8557,"lng":-97.6932,"tier":"good","sat":"G19","age_sec":434,"frp":63.0,"tempK":431.8},{"lat":39.812,"lng":-117.3273,"tier":"good","sat":"G18","age_sec":433,"frp":59.9,"tempK":430.5},{"lat":25.5779,"lng":-99.9419,"tier":"good","sat":"G19","age_sec":434,"frp":39.4,"tempK":580.4},{"lat":17.9749,"lng":-77.0361,"tier":"good","sat":"G19","age_sec":434,"frp":23.0,"tempK":453.7},{"lat":21.2007,"lng":-77.7122,"tier":"good","sat":"G19","age_sec":434,"frp":19.9,"tempK":522.2}]}