{"generated_at":"2026-06-07T21:49:54Z","newest_granule":"2026-06-07T21:46:20Z","product":"GOES-R ABI L2 FDC (Fire/Hot Spot Characterization), CONUS sector, 2km","counts":{"total":15,"g19":14,"g18":2},"detections":[{"lat":39.2302,"lng":-112.1331,"tier":"good","sat":"G18","age_sec":214,"frp":821.0,"tempK":760.1},{"lat":39.2027,"lng":-112.1452,"tier":"good","sat":"G18","age_sec":214,"frp":338.1,"tempK":752.3},{"lat":28.7172,"lng":-109.0577,"tier":"high","sat":"G19","age_sec":516,"frp":182.1},{"lat":28.7404,"lng":-109.0681,"tier":"high","sat":"G19","age_sec":516,"frp":177.5},{"lat":24.8766,"lng":-106.1996,"tier":"good","sat":"G19","age_sec":516,"frp":95.8,"tempK":404.2},{"lat":18.8039,"lng":-89.3691,"tier":"good","sat":"G19","age_sec":516,"frp":71.5,"tempK":685.4},{"lat":24.7022,"lng":-106.6785,"tier":"good","sat":"G19","age_sec":516,"frp":53.1,"tempK":619.6},{"lat":32.9332,"lng":-101.1705,"tier":"good","sat":"G19","age_sec":516,"frp":50.9,"tempK":453.0},{"lat":31.714,"lng":-81.6137,"tier":"good","sat":"G19","age_sec":516,"frp":49.7,"tempK":438.1},{"lat":18.8987,"lng":-89.056,"tier":"good","sat":"G19","age_sec":516,"frp":40.8,"tempK":506.7},{"lat":25.069,"lng":-106.7284,"tier":"good","sat":"G19","age_sec":516,"frp":35.9,"tempK":499.4},{"lat":18.834,"lng":-88.6871,"tier":"good","sat":"G19","age_sec":516,"frp":34.8,"tempK":736.5},{"lat":16.7183,"lng":-89.2058,"tier":"good","sat":"G19","age_sec":516,"frp":27.0,"tempK":487.0},{"lat":35.7745,"lng":-79.8079,"tier":"good","sat":"G19","age_sec":516,"frp":26.7,"tempK":535.3},{"lat":16.4473,"lng":-89.3205,"tier":"good","sat":"G19","age_sec":516,"frp":24.8,"tempK":513.9}]}