{"generated_at":"2026-07-10T17:46:22Z","newest_granule":"2026-07-10T17:41:18Z","product":"GOES-R ABI L2 FDC (Fire/Hot Spot Characterization), CONUS sector, 2km","counts":{"total":9,"g19":8,"g18":1},"detections":[{"lat":50.2333,"lng":-78.5735,"tier":"good","sat":"G19","age_sec":305,"frp":245.5,"tempK":547.3},{"lat":50.1973,"lng":-78.5705,"tier":"good","sat":"G19","age_sec":305,"frp":239.0,"tempK":552.9},{"lat":50.1613,"lng":-78.5675,"tier":"good","sat":"G19","age_sec":305,"frp":209.5,"tempK":512.7},{"lat":50.4854,"lng":-78.4732,"tier":"good","sat":"G19","age_sec":305,"frp":190.5,"tempK":538.8},{"lat":33.3435,"lng":-108.5993,"tier":"good","sat":"G19","age_sec":305,"frp":77.3,"tempK":447.1},{"lat":33.3485,"lng":-108.5543,"tier":"good","sat":"G18","age_sec":304,"frp":53.4,"tempK":415.3},{"lat":36.4215,"lng":-100.8051,"tier":"good","sat":"G19","age_sec":305,"frp":48.1,"tempK":464.7},{"lat":36.4202,"lng":-100.7775,"tier":"good","sat":"G19","age_sec":305,"frp":43.9,"tempK":600.8},{"lat":31.6037,"lng":-94.7533,"tier":"good","sat":"G19","age_sec":305,"frp":34.4,"tempK":408.6}]}