{"generated_at":"2026-06-19T01:34:08Z","newest_granule":"2026-06-19T01:26:20Z","product":"GOES-R ABI L2 FDC (Fire/Hot Spot Characterization), CONUS sector, 2km","counts":{"total":18,"g19":14,"g18":4},"detections":[{"lat":37.409,"lng":-114.3053,"tier":"good","sat":"G19","age_sec":469,"frp":1967.5,"tempK":1154.0},{"lat":37.3896,"lng":-114.2362,"tier":"good","sat":"G18","age_sec":468,"frp":1091.1,"tempK":1641.5},{"lat":37.416,"lng":-114.2263,"tier":"high","sat":"G18","age_sec":468,"frp":1071.7},{"lat":38.1567,"lng":-113.7122,"tier":"high","sat":"G19","age_sec":469,"frp":590.7},{"lat":35.4087,"lng":-119.8416,"tier":"good","sat":"G19","age_sec":469,"frp":585.2,"tempK":628.8},{"lat":35.403,"lng":-119.8111,"tier":"good","sat":"G18","age_sec":468,"frp":403.2,"tempK":666.8},{"lat":37.4366,"lng":-114.3259,"tier":"high","sat":"G19","age_sec":469,"frp":374.3},{"lat":43.289,"lng":-120.2557,"tier":"high","sat":"G19","age_sec":469,"frp":283.7},{"lat":35.3818,"lng":-119.8185,"tier":"good","sat":"G19","age_sec":469,"frp":264.9,"tempK":767.4},{"lat":35.4282,"lng":-119.8047,"tier":"good","sat":"G18","age_sec":468,"frp":145.7,"tempK":575.7},{"lat":44.542,"lng":-115.2506,"tier":"high","sat":"G19","age_sec":469,"frp":94.2},{"lat":47.9603,"lng":-106.5972,"tier":"high","sat":"G19","age_sec":469,"frp":71.4},{"lat":17.2783,"lng":-88.7195,"tier":"good","sat":"G19","age_sec":469,"frp":51.8,"tempK":938.1},{"lat":31.8789,"lng":-112.8682,"tier":"good","sat":"G19","age_sec":469,"frp":37.5,"tempK":468.1},{"lat":18.5047,"lng":-96.1494,"tier":"good","sat":"G19","age_sec":469,"frp":34.3,"tempK":577.4},{"lat":17.9495,"lng":-90.4308,"tier":"good","sat":"G19","age_sec":469,"frp":33.4,"tempK":624.3},{"lat":18.2978,"lng":-92.4923,"tier":"medium","sat":"G19","age_sec":469,"frp":25.6},{"lat":25.7817,"lng":-80.467,"tier":"medium","sat":"G19","age_sec":469,"frp":18.8}]}