{"generated_at":"2026-06-20T19:04:40Z","newest_granule":"2026-06-20T19:01:20Z","product":"GOES-R ABI L2 FDC (Fire/Hot Spot Characterization), CONUS sector, 2km","counts":{"total":53,"g19":41,"g18":15},"detections":[{"lat":40.0733,"lng":-112.1227,"tier":"high","sat":"G18","age_sec":200,"frp":2792.2},{"lat":40.0438,"lng":-112.1642,"tier":"good","sat":"G18","age_sec":200,"frp":2689.4,"tempK":942.0},{"lat":40.0718,"lng":-112.1516,"tier":"good","sat":"G18","age_sec":200,"frp":2242.5,"tempK":828.7},{"lat":40.0186,"lng":-112.1994,"tier":"high","sat":"G19","age_sec":201,"frp":2085.6},{"lat":40.0158,"lng":-112.1768,"tier":"good","sat":"G18","age_sec":200,"frp":1831.4,"tempK":893.8},{"lat":39.9891,"lng":-112.1606,"tier":"good","sat":"G18","age_sec":200,"frp":967.7,"tempK":1373.4},{"lat":40.05,"lng":-112.2569,"tier":"high","sat":"G19","age_sec":201,"frp":573.6},{"lat":39.9877,"lng":-112.1894,"tier":"good","sat":"G18","age_sec":200,"frp":526.5,"tempK":2293.4},{"lat":40.0999,"lng":-112.1389,"tier":"good","sat":"G18","age_sec":200,"frp":433.7,"tempK":756.8},{"lat":40.1013,"lng":-112.11,"tier":"high","sat":"G18","age_sec":200,"frp":417.6},{"lat":37.411,"lng":-114.7158,"tier":"high","sat":"G19","age_sec":201,"frp":373.5},{"lat":37.4135,"lng":-114.752,"tier":"high","sat":"G19","age_sec":201,"frp":373.1},{"lat":37.4217,"lng":-114.7001,"tier":"high","sat":"G18","age_sec":200,"frp":364.2},{"lat":17.3937,"lng":-88.5508,"tier":"good","sat":"G19","age_sec":201,"frp":263.5,"tempK":649.1},{"lat":37.4366,"lng":-114.3259,"tier":"good","sat":"G19","age_sec":201,"frp":258.4,"tempK":748.1},{"lat":18.8901,"lng":-88.4314,"tier":"good","sat":"G19","age_sec":201,"frp":226.3,"tempK":869.3},{"lat":37.4341,"lng":-114.29,"tier":"good","sat":"G19","age_sec":201,"frp":215.3,"tempK":486.3},{"lat":37.4401,"lng":-114.2704,"tier":"good","sat":"G18","age_sec":200,"frp":214.3,"tempK":495.2},{"lat":50.2418,"lng":-121.5478,"tier":"good","sat":"G18","age_sec":200,"frp":208.3,"tempK":407.3},{"lat":19.3462,"lng":-89.731,"tier":"good","sat":"G19","age_sec":201,"frp":190.9,"tempK":715.0},{"lat":40.0424,"lng":-112.193,"tier":"high","sat":"G18","age_sec":200,"frp":190.9},{"lat":18.8702,"lng":-88.4295,"tier":"good","sat":"G19","age_sec":201,"frp":184.9,"tempK":744.7},{"lat":19.3459,"lng":-89.7106,"tier":"good","sat":"G19","age_sec":201,"frp":165.8,"tempK":496.4},{"lat":18.8898,"lng":-88.4113,"tier":"good","sat":"G19","age_sec":201,"frp":165.2,"tempK":681.8},{"lat":25.824,"lng":-80.4077,"tier":"good","sat":"G19","age_sec":201,"frp":156.4,"tempK":495.0},{"lat":33.6614,"lng":-110.7083,"tier":"good","sat":"G18","age_sec":200,"frp":155.0,"tempK":558.7},{"lat":36.7819,"lng":-101.3935,"tier":"high","sat":"G19","age_sec":201,"frp":149.6},{"lat":33.6563,"lng":-110.7245,"tier":"good","sat":"G19","age_sec":201,"frp":140.7,"tempK":509.8},{"lat":33.6581,"lng":-110.7558,"tier":"good","sat":"G19","age_sec":201,"frp":132.9,"tempK":643.4},{"lat":18.8699,"lng":-88.4094,"tier":"good","sat":"G19","age_sec":201,"frp":130.3,"tempK":916.8},{"lat":17.854,"lng":-93.1176,"tier":"good","sat":"G19","age_sec":201,"frp":121.1,"tempK":1255.6},{"lat":18.25,"lng":-91.9929,"tier":"high","sat":"G19","age_sec":201,"frp":112.9},{"lat":19.3262,"lng":-89.7288,"tier":"good","sat":"G19","age_sec":201,"frp":107.2,"tempK":439.3},{"lat":17.8343,"lng":-93.1151,"tier":"high","sat":"G19","age_sec":201,"frp":104.4},{"lat":17.3934,"lng":-88.5309,"tier":"good","sat":"G19","age_sec":201,"frp":101.6,"tempK":579.1},{"lat":19.9544,"lng":-77.6084,"tier":"good","sat":"G19","age_sec":201,"frp":99.1,"tempK":513.6},{"lat":37.4665,"lng":-114.2605,"tier":"medium","sat":"G18","age_sec":200,"frp":96.8},{"lat":36.7833,"lng":-101.4214,"tier":"medium","sat":"G19","age_sec":201,"frp":92.2},{"lat":19.3259,"lng":-89.7084,"tier":"good","sat":"G19","age_sec":201,"frp":86.6,"tempK":409.7},{"lat":30.9232,"lng":-87.3445,"tier":"good","sat":"G19","age_sec":201,"frp":84.9,"tempK":529.8},{"lat":37.4412,"lng":-114.2434,"tier":"good","sat":"G18","age_sec":200,"frp":80.8,"tempK":415.8},{"lat":19.2449,"lng":-89.6184,"tier":"good","sat":"G19","age_sec":201,"frp":76.3,"tempK":496.5},{"lat":17.9795,"lng":-71.3169,"tier":"good","sat":"G19","age_sec":201,"frp":75.5,"tempK":400.7},{"lat":18.8375,"lng":-90.3047,"tier":"good","sat":"G19","age_sec":201,"frp":63.3,"tempK":494.2},{"lat":18.8372,"lng":-90.2843,"tier":"good","sat":"G19","age_sec":201,"frp":60.8,"tempK":492.1},{"lat":16.1542,"lng":-90.6902,"tier":"good","sat":"G19","age_sec":201,"frp":58.4,"tempK":610.4},{"lat":19.4016,"lng":-89.4325,"tier":"good","sat":"G19","age_sec":201,"frp":57.9,"tempK":439.0},{"lat":21.2697,"lng":-87.8442,"tier":"good","sat":"G19","age_sec":201,"frp":50.5,"tempK":482.0},{"lat":17.8946,"lng":-93.1848,"tier":"good","sat":"G19","age_sec":201,"frp":49.3,"tempK":444.1},{"lat":15.3604,"lng":-90.6748,"tier":"good","sat":"G19","age_sec":201,"frp":49.2,"tempK":405.9},{"lat":18.4831,"lng":-89.0945,"tier":"good","sat":"G19","age_sec":201,"frp":48.7,"tempK":564.5},{"lat":17.5687,"lng":-95.881,"tier":"good","sat":"G19","age_sec":201,"frp":46.5,"tempK":440.2},{"lat":18.1211,"lng":-91.3435,"tier":"good","sat":"G19","age_sec":201,"frp":18.4,"tempK":473.3}]}