{"generated_at":"2026-07-22T01:42:52Z","newest_granule":"2026-07-22T01:36:17Z","product":"GOES-R ABI L2 FDC (Fire/Hot Spot Characterization), CONUS sector, 2km","counts":{"total":31,"g19":10,"g18":21},"detections":[{"lat":49.819,"lng":-121.4208,"tier":"good","sat":"G18","age_sec":395,"frp":2169.2,"tempK":675.1},{"lat":49.8203,"lng":-121.389,"tier":"good","sat":"G18","age_sec":395,"frp":2047.2,"tempK":795.3},{"lat":49.8524,"lng":-121.4712,"tier":"good","sat":"G18","age_sec":395,"frp":1490.6,"tempK":644.5},{"lat":49.8177,"lng":-121.4526,"tier":"good","sat":"G18","age_sec":395,"frp":979.5,"tempK":580.5},{"lat":49.8165,"lng":-121.4845,"tier":"good","sat":"G18","age_sec":395,"frp":844.1,"tempK":648.9},{"lat":50.2807,"lng":-122.3865,"tier":"good","sat":"G18","age_sec":395,"frp":581.2,"tempK":1470.3},{"lat":48.9443,"lng":-120.5958,"tier":"good","sat":"G18","age_sec":395,"frp":571.8,"tempK":543.2},{"lat":49.9283,"lng":-121.3489,"tier":"high","sat":"G18","age_sec":395,"frp":462.9},{"lat":49.8935,"lng":-121.3304,"tier":"high","sat":"G18","age_sec":395,"frp":356.2},{"lat":44.1342,"lng":-123.0856,"tier":"high","sat":"G19","age_sec":395,"frp":347.4},{"lat":44.105,"lng":-123.0936,"tier":"high","sat":"G19","age_sec":395,"frp":345.3},{"lat":49.8575,"lng":-121.3437,"tier":"high","sat":"G18","age_sec":395,"frp":307.4},{"lat":36.9938,"lng":-118.3882,"tier":"high","sat":"G19","age_sec":395,"frp":258.3},{"lat":49.7843,"lng":-121.4023,"tier":"good","sat":"G18","age_sec":395,"frp":254.6,"tempK":527.5},{"lat":50.2431,"lng":-122.4312,"tier":"good","sat":"G18","age_sec":395,"frp":250.9,"tempK":573.0},{"lat":49.8512,"lng":-121.5031,"tier":"high","sat":"G18","age_sec":395,"frp":229.0},{"lat":49.8884,"lng":-121.458,"tier":"good","sat":"G18","age_sec":395,"frp":226.4,"tempK":518.9},{"lat":49.7831,"lng":-121.4341,"tier":"good","sat":"G18","age_sec":395,"frp":223.9,"tempK":465.1},{"lat":48.1848,"lng":-119.2281,"tier":"good","sat":"G18","age_sec":395,"frp":183.6,"tempK":995.4},{"lat":48.2702,"lng":-118.8235,"tier":"good","sat":"G18","age_sec":395,"frp":135.4,"tempK":598.1},{"lat":17.8343,"lng":-93.1151,"tier":"high","sat":"G19","age_sec":395,"frp":85.0},{"lat":37.6328,"lng":-121.8231,"tier":"good","sat":"G18","age_sec":395,"frp":74.2,"tempK":838.6},{"lat":26.3631,"lng":-80.8091,"tier":"high","sat":"G19","age_sec":395,"frp":70.3},{"lat":48.0163,"lng":-120.848,"tier":"good","sat":"G18","age_sec":395,"frp":64.1,"tempK":548.9},{"lat":33.3528,"lng":-117.3813,"tier":"good","sat":"G18","age_sec":395,"frp":53.3,"tempK":432.3},{"lat":21.6077,"lng":-78.1934,"tier":"good","sat":"G19","age_sec":395,"frp":50.2,"tempK":669.3},{"lat":36.9721,"lng":-121.437,"tier":"good","sat":"G18","age_sec":395,"frp":30.4,"tempK":579.4},{"lat":22.2214,"lng":-78.7441,"tier":"good","sat":"G19","age_sec":395,"frp":27.2,"tempK":433.1},{"lat":22.8233,"lng":-80.0189,"tier":"high","sat":"G19","age_sec":395,"frp":26.7},{"lat":18.4579,"lng":-88.6904,"tier":"high","sat":"G19","age_sec":395,"frp":24.4},{"lat":18.4287,"lng":-93.1916,"tier":"good","sat":"G19","age_sec":395,"frp":23.2,"tempK":449.5}]}