{"generated_at":"2026-06-15T19:17:17Z","newest_granule":"2026-06-15T19:11:19Z","product":"GOES-R ABI L2 FDC (Fire/Hot Spot Characterization), CONUS sector, 2km","counts":{"total":34,"g19":26,"g18":11},"detections":[{"lat":27.7141,"lng":-81.3326,"tier":"good","sat":"G19","age_sec":358,"frp":1298.7,"tempK":796.8},{"lat":46.4005,"lng":-118.8399,"tier":"good","sat":"G19","age_sec":358,"frp":1290.9,"tempK":638.3},{"lat":46.396,"lng":-118.8498,"tier":"good","sat":"G18","age_sec":358,"frp":1225.2,"tempK":620.5},{"lat":27.736,"lng":-81.3341,"tier":"good","sat":"G19","age_sec":358,"frp":1192.7,"tempK":770.4},{"lat":46.4048,"lng":-118.888,"tier":"good","sat":"G19","age_sec":358,"frp":662.7,"tempK":593.3},{"lat":27.7139,"lng":-81.3116,"tier":"good","sat":"G19","age_sec":358,"frp":643.6,"tempK":694.8},{"lat":46.3947,"lng":-118.88,"tier":"good","sat":"G18","age_sec":358,"frp":471.6,"tempK":675.1},{"lat":46.3961,"lng":-118.7916,"tier":"good","sat":"G19","age_sec":358,"frp":439.2,"tempK":604.7},{"lat":19.406,"lng":-155.2821,"tier":"good","sat":"G18","age_sec":358,"frp":420.1,"tempK":429.2},{"lat":46.4315,"lng":-118.8336,"tier":"high","sat":"G19","age_sec":358,"frp":290.3},{"lat":46.3692,"lng":-118.8458,"tier":"good","sat":"G19","age_sec":358,"frp":277.4,"tempK":405.1},{"lat":46.3649,"lng":-118.7977,"tier":"good","sat":"G19","age_sec":358,"frp":266.2,"tempK":547.7},{"lat":27.7143,"lng":-81.3536,"tier":"good","sat":"G19","age_sec":358,"frp":261.1,"tempK":838.8},{"lat":36.862,"lng":-89.4054,"tier":"good","sat":"G19","age_sec":358,"frp":218.1,"tempK":638.0},{"lat":19.4261,"lng":-155.2849,"tier":"good","sat":"G18","age_sec":358,"frp":216.2,"tempK":437.3},{"lat":46.3634,"lng":-118.8625,"tier":"good","sat":"G18","age_sec":358,"frp":199.3,"tempK":401.9},{"lat":27.7362,"lng":-81.3551,"tier":"good","sat":"G19","age_sec":358,"frp":178.4,"tempK":742.4},{"lat":19.4056,"lng":-155.2611,"tier":"good","sat":"G18","age_sec":358,"frp":175.0,"tempK":486.0},{"lat":36.8627,"lng":-89.43,"tier":"good","sat":"G19","age_sec":358,"frp":150.4,"tempK":664.9},{"lat":19.4064,"lng":-155.303,"tier":"high","sat":"G18","age_sec":358,"frp":136.4},{"lat":25.8243,"lng":-80.4488,"tier":"high","sat":"G19","age_sec":358,"frp":110.0},{"lat":19.4257,"lng":-155.2639,"tier":"good","sat":"G18","age_sec":358,"frp":101.9,"tempK":470.4},{"lat":36.1841,"lng":-89.7425,"tier":"good","sat":"G19","age_sec":358,"frp":68.0,"tempK":412.4},{"lat":27.6875,"lng":-80.8064,"tier":"good","sat":"G19","age_sec":358,"frp":50.4,"tempK":450.0},{"lat":30.4395,"lng":-86.032,"tier":"good","sat":"G19","age_sec":358,"frp":44.9,"tempK":403.5},{"lat":16.2621,"lng":-90.0405,"tier":"good","sat":"G19","age_sec":358,"frp":37.3,"tempK":429.7},{"lat":16.9016,"lng":-98.0032,"tier":"good","sat":"G19","age_sec":358,"frp":35.7,"tempK":407.6},{"lat":36.0367,"lng":-115.3927,"tier":"good","sat":"G18","age_sec":358,"frp":32.0,"tempK":573.9},{"lat":17.8828,"lng":-92.4823,"tier":"good","sat":"G19","age_sec":358,"frp":31.1,"tempK":424.7},{"lat":20.9556,"lng":-88.5441,"tier":"good","sat":"G19","age_sec":358,"frp":30.8,"tempK":405.5},{"lat":16.0997,"lng":-92.3387,"tier":"good","sat":"G19","age_sec":358,"frp":26.1,"tempK":478.5},{"lat":19.1179,"lng":-90.4382,"tier":"good","sat":"G19","age_sec":358,"frp":24.2,"tempK":499.9},{"lat":19.6369,"lng":-71.9134,"tier":"good","sat":"G19","age_sec":358,"frp":24.1,"tempK":450.4},{"lat":16.1826,"lng":-89.8935,"tier":"good","sat":"G19","age_sec":358,"frp":24.0,"tempK":462.6}]}