{"generated_at":"2026-07-21T20:16:39Z","newest_granule":"2026-07-21T20:11:17Z","product":"GOES-R ABI L2 FDC (Fire/Hot Spot Characterization), CONUS sector, 2km","counts":{"total":54,"g19":51,"g18":9},"detections":[{"lat":36.9909,"lng":-118.3488,"tier":"good","sat":"G19","age_sec":322,"frp":1680.7,"tempK":804.7},{"lat":36.988,"lng":-118.3095,"tier":"good","sat":"G19","age_sec":322,"frp":755.5,"tempK":554.0},{"lat":36.9632,"lng":-118.325,"tier":"good","sat":"G19","age_sec":322,"frp":618.1,"tempK":561.3},{"lat":51.3765,"lng":-122.4245,"tier":"good","sat":"G19","age_sec":322,"frp":477.4,"tempK":733.1},{"lat":36.9975,"lng":-118.3022,"tier":"high","sat":"G18","age_sec":322,"frp":414.5},{"lat":48.9443,"lng":-120.5958,"tier":"good","sat":"G18","age_sec":322,"frp":389.4,"tempK":710.1},{"lat":51.3395,"lng":-122.4173,"tier":"good","sat":"G19","age_sec":322,"frp":378.9,"tempK":521.4},{"lat":44.4166,"lng":-121.5479,"tier":"high","sat":"G19","age_sec":322,"frp":350.4},{"lat":26.3631,"lng":-80.8091,"tier":"good","sat":"G19","age_sec":322,"frp":277.0,"tempK":631.3},{"lat":20.6118,"lng":-74.9513,"tier":"good","sat":"G19","age_sec":322,"frp":223.4,"tempK":486.4},{"lat":48.1257,"lng":-118.2971,"tier":"good","sat":"G18","age_sec":322,"frp":205.0,"tempK":879.8},{"lat":50.2795,"lng":-122.4185,"tier":"good","sat":"G18","age_sec":322,"frp":200.0,"tempK":741.6},{"lat":49.9445,"lng":-121.5932,"tier":"good","sat":"G19","age_sec":322,"frp":173.7,"tempK":528.7},{"lat":20.6521,"lng":-75.0292,"tier":"good","sat":"G19","age_sec":322,"frp":135.7,"tempK":502.6},{"lat":17.8343,"lng":-93.1151,"tier":"good","sat":"G19","age_sec":322,"frp":130.5,"tempK":838.4},{"lat":17.854,"lng":-93.1176,"tier":"good","sat":"G19","age_sec":322,"frp":121.0,"tempK":1032.5},{"lat":49.1708,"lng":-120.9752,"tier":"medium","sat":"G18","age_sec":322,"frp":108.2},{"lat":18.1145,"lng":-90.9152,"tier":"good","sat":"G19","age_sec":322,"frp":107.3,"tempK":514.4},{"lat":24.236,"lng":-97.8752,"tier":"good","sat":"G19","age_sec":322,"frp":106.7,"tempK":560.6},{"lat":17.8946,"lng":-93.1848,"tier":"good","sat":"G19","age_sec":322,"frp":104.8,"tempK":509.2},{"lat":49.9219,"lng":-121.5085,"tier":"good","sat":"G18","age_sec":322,"frp":103.9,"tempK":527.3},{"lat":27.0151,"lng":-109.4503,"tier":"good","sat":"G19","age_sec":322,"frp":95.4,"tempK":400.5},{"lat":24.2354,"lng":-97.8523,"tier":"good","sat":"G19","age_sec":322,"frp":94.4,"tempK":524.9},{"lat":40.2297,"lng":-108.1642,"tier":"good","sat":"G18","age_sec":322,"frp":92.2,"tempK":403.8},{"lat":40.2461,"lng":-108.2019,"tier":"good","sat":"G19","age_sec":322,"frp":91.5,"tempK":502.1},{"lat":20.6319,"lng":-74.9513,"tier":"good","sat":"G19","age_sec":322,"frp":87.0,"tempK":401.3},{"lat":18.1142,"lng":-90.8949,"tier":"good","sat":"G19","age_sec":322,"frp":86.4,"tempK":455.7},{"lat":26.3629,"lng":-80.7884,"tier":"good","sat":"G19","age_sec":322,"frp":82.5,"tempK":494.9},{"lat":18.0947,"lng":-90.913,"tier":"good","sat":"G19","age_sec":322,"frp":76.3,"tempK":497.0},{"lat":26.1852,"lng":-98.692,"tier":"good","sat":"G19","age_sec":322,"frp":74.3,"tempK":1079.0},{"lat":17.8544,"lng":-91.9458,"tier":"good","sat":"G19","age_sec":322,"frp":72.3,"tempK":638.8},{"lat":32.21,"lng":-114.866,"tier":"good","sat":"G19","age_sec":322,"frp":66.8,"tempK":400.7},{"lat":48.0163,"lng":-120.848,"tier":"good","sat":"G18","age_sec":322,"frp":63.9,"tempK":473.9},{"lat":37.5476,"lng":-96.5822,"tier":"good","sat":"G19","age_sec":322,"frp":61.5,"tempK":597.8},{"lat":19.5859,"lng":-89.7372,"tier":"medium","sat":"G19","age_sec":322,"frp":60.0},{"lat":17.7161,"lng":-93.1209,"tier":"good","sat":"G19","age_sec":322,"frp":55.3,"tempK":480.0},{"lat":19.7519,"lng":-88.801,"tier":"good","sat":"G19","age_sec":322,"frp":49.4,"tempK":415.8},{"lat":30.9177,"lng":-89.2309,"tier":"good","sat":"G19","age_sec":322,"frp":48.9,"tempK":518.0},{"lat":17.8347,"lng":-91.9435,"tier":"high","sat":"G19","age_sec":322,"frp":47.6},{"lat":23.9704,"lng":-98.179,"tier":"good","sat":"G19","age_sec":322,"frp":41.5,"tempK":774.9},{"lat":21.6058,"lng":-77.6228,"tier":"good","sat":"G19","age_sec":322,"frp":37.5,"tempK":478.0},{"lat":16.7159,"lng":-90.5049,"tier":"good","sat":"G19","age_sec":322,"frp":36.2,"tempK":426.2},{"lat":17.8548,"lng":-91.9663,"tier":"good","sat":"G19","age_sec":322,"frp":34.2,"tempK":576.7},{"lat":18.0579,"lng":-71.3342,"tier":"good","sat":"G19","age_sec":322,"frp":33.2,"tempK":444.7},{"lat":17.8828,"lng":-92.4823,"tier":"good","sat":"G19","age_sec":322,"frp":31.5,"tempK":423.3},{"lat":33.5537,"lng":-95.555,"tier":"good","sat":"G19","age_sec":322,"frp":31.4,"tempK":490.8},{"lat":21.0373,"lng":-77.0823,"tier":"good","sat":"G19","age_sec":322,"frp":30.0,"tempK":434.0},{"lat":33.8823,"lng":-91.4811,"tier":"good","sat":"G19","age_sec":322,"frp":29.4,"tempK":415.5},{"lat":18.9542,"lng":-90.1347,"tier":"good","sat":"G19","age_sec":322,"frp":29.1,"tempK":418.4},{"lat":17.9127,"lng":-91.8913,"tier":"good","sat":"G19","age_sec":322,"frp":28.1,"tempK":576.9},{"lat":18.1652,"lng":-91.6346,"tier":"good","sat":"G19","age_sec":322,"frp":27.3,"tempK":562.6},{"lat":19.8492,"lng":-88.6087,"tier":"good","sat":"G19","age_sec":322,"frp":27.2,"tempK":414.6},{"lat":17.7005,"lng":-92.1733,"tier":"good","sat":"G19","age_sec":322,"frp":26.9,"tempK":444.7},{"lat":20.1909,"lng":-74.3301,"tier":"good","sat":"G19","age_sec":322,"frp":18.9,"tempK":468.4}]}