{"generated_at":"2026-06-04T13:38:35Z","newest_granule":"2026-06-04T13:31:19Z","product":"GOES-R ABI L2 FDC (Fire/Hot Spot Characterization), CONUS sector, 2km","counts":{"total":8,"g19":5,"g18":3},"detections":[{"lat":44.7901,"lng":-100.9481,"tier":"high","sat":"G18","age_sec":436,"frp":62.1},{"lat":35.8602,"lng":-77.7789,"tier":"high","sat":"G19","age_sec":438,"frp":55.1},{"lat":27.0113,"lng":-109.3662,"tier":"good","sat":"G19","age_sec":438,"frp":43.2,"tempK":433.5},{"lat":41.376,"lng":-110.6077,"tier":"high","sat":"G18","age_sec":436,"frp":42.0},{"lat":29.4987,"lng":-99.113,"tier":"good","sat":"G19","age_sec":438,"frp":32.8,"tempK":712.2},{"lat":34.5646,"lng":-80.2036,"tier":"good","sat":"G19","age_sec":438,"frp":29.7,"tempK":504.4},{"lat":19.406,"lng":-155.2821,"tier":"good","sat":"G18","age_sec":436,"frp":26.3,"tempK":415.7},{"lat":17.7521,"lng":-92.9191,"tier":"good","sat":"G19","age_sec":438,"frp":25.4,"tempK":418.5}]}