{"generated_at":"2026-06-26T19:39:01Z","newest_granule":"2026-06-26T19:31:22Z","product":"GOES-R ABI L2 FDC (Fire/Hot Spot Characterization), CONUS sector, 2km","counts":{"total":63,"g19":43,"g18":38},"detections":[{"lat":38.3836,"lng":-112.3704,"tier":"good","sat":"G19","age_sec":464,"frp":3841.5,"tempK":781.0},{"lat":38.4115,"lng":-112.3905,"tier":"high","sat":"G19","age_sec":464,"frp":3429.8},{"lat":38.3627,"lng":-112.4549,"tier":"good","sat":"G19","age_sec":464,"frp":3379.6,"tempK":1059.4},{"lat":38.4092,"lng":-112.3557,"tier":"high","sat":"G19","age_sec":464,"frp":3232.7},{"lat":38.3944,"lng":-112.2997,"tier":"good","sat":"G18","age_sec":459,"frp":3022.9,"tempK":657.9},{"lat":38.3324,"lng":-112.4904,"tier":"good","sat":"G18","age_sec":459,"frp":2944.9,"tempK":772.7},{"lat":38.3634,"lng":-112.3952,"tier":"good","sat":"G18","age_sec":459,"frp":2699.7,"tempK":1079.5},{"lat":38.386,"lng":-112.4053,"tier":"high","sat":"G19","age_sec":464,"frp":2141.5},{"lat":38.3442,"lng":-112.5745,"tier":"good","sat":"G19","age_sec":464,"frp":2122.2,"tempK":972.4},{"lat":38.3337,"lng":-112.4624,"tier":"high","sat":"G18","age_sec":459,"frp":2109.3},{"lat":38.314,"lng":-112.5195,"tier":"good","sat":"G19","age_sec":464,"frp":1882.0,"tempK":2394.7},{"lat":38.1201,"lng":-114.3323,"tier":"high","sat":"G19","age_sec":464,"frp":1832.6},{"lat":38.3311,"lng":-112.5183,"tier":"good","sat":"G18","age_sec":459,"frp":1811.5,"tempK":733.7},{"lat":38.3931,"lng":-112.3277,"tier":"good","sat":"G18","age_sec":459,"frp":1770.8,"tempK":837.2},{"lat":38.3163,"lng":-112.5543,"tier":"good","sat":"G19","age_sec":464,"frp":1735.3,"tempK":1035.3},{"lat":38.335,"lng":-112.4345,"tier":"high","sat":"G18","age_sec":459,"frp":1567.1},{"lat":38.3813,"lng":-112.3357,"tier":"good","sat":"G19","age_sec":464,"frp":1535.1,"tempK":1305.1},{"lat":38.3957,"lng":-112.2717,"tier":"high","sat":"G18","age_sec":459,"frp":1463.5},{"lat":38.4201,"lng":-112.3163,"tier":"high","sat":"G18","age_sec":459,"frp":1273.6},{"lat":38.3581,"lng":-112.507,"tier":"high","sat":"G18","age_sec":459,"frp":935.9},{"lat":38.3116,"lng":-112.4845,"tier":"high","sat":"G19","age_sec":464,"frp":769.1},{"lat":38.0922,"lng":-114.3109,"tier":"good","sat":"G19","age_sec":464,"frp":750.8,"tempK":2728.9},{"lat":38.3364,"lng":-112.4065,"tier":"good","sat":"G18","age_sec":459,"frp":715.0,"tempK":1306.9},{"lat":38.4139,"lng":-112.4254,"tier":"high","sat":"G19","age_sec":464,"frp":711.4},{"lat":38.3687,"lng":-112.2832,"tier":"good","sat":"G18","age_sec":459,"frp":618.1,"tempK":1029.7},{"lat":37.4292,"lng":-114.2186,"tier":"good","sat":"G19","age_sec":464,"frp":587.2,"tempK":615.2},{"lat":37.4183,"lng":-114.1725,"tier":"good","sat":"G18","age_sec":459,"frp":534.5,"tempK":616.5},{"lat":38.1191,"lng":-114.2808,"tier":"high","sat":"G18","age_sec":459,"frp":521.2},{"lat":37.4017,"lng":-114.198,"tier":"good","sat":"G19","age_sec":464,"frp":478.0,"tempK":738.3},{"lat":38.0936,"lng":-114.2638,"tier":"high","sat":"G18","age_sec":459,"frp":448.5},{"lat":37.4567,"lng":-114.2391,"tier":"high","sat":"G19","age_sec":464,"frp":443.2},{"lat":38.1203,"lng":-114.2536,"tier":"high","sat":"G18","age_sec":459,"frp":440.8},{"lat":38.2234,"lng":-112.3551,"tier":"good","sat":"G19","age_sec":464,"frp":389.7,"tempK":554.2},{"lat":37.4435,"lng":-114.1895,"tier":"good","sat":"G18","age_sec":459,"frp":317.8,"tempK":718.6},{"lat":38.3081,"lng":-112.4458,"tier":"high","sat":"G18","age_sec":459,"frp":299.3},{"lat":38.1176,"lng":-114.2961,"tier":"high","sat":"G19","age_sec":464,"frp":292.8},{"lat":38.1226,"lng":-114.3685,"tier":"high","sat":"G19","age_sec":464,"frp":292.1},{"lat":38.3721,"lng":-112.5947,"tier":"high","sat":"G19","age_sec":464,"frp":291.2},{"lat":38.3534,"lng":-112.3157,"tier":"high","sat":"G19","age_sec":464,"frp":285.2},{"lat":38.2512,"lng":-112.3749,"tier":"good","sat":"G19","age_sec":464,"frp":282.0,"tempK":656.6},{"lat":38.2258,"lng":-112.3899,"tier":"high","sat":"G19","age_sec":464,"frp":265.8},{"lat":38.2352,"lng":-112.3121,"tier":"good","sat":"G18","age_sec":459,"frp":265.2,"tempK":595.7},{"lat":38.2536,"lng":-112.4098,"tier":"high","sat":"G19","age_sec":464,"frp":226.4},{"lat":37.4317,"lng":-114.2543,"tier":"good","sat":"G19","age_sec":464,"frp":189.9,"tempK":469.1},{"lat":37.3919,"lng":-114.1823,"tier":"high","sat":"G18","age_sec":459,"frp":180.0},{"lat":37.4699,"lng":-114.1797,"tier":"high","sat":"G18","age_sec":459,"frp":161.8},{"lat":37.4042,"lng":-114.2338,"tier":"good","sat":"G19","age_sec":464,"frp":158.7,"tempK":624.4},{"lat":38.3466,"lng":-112.6095,"tier":"good","sat":"G19","age_sec":464,"frp":145.7,"tempK":462.5},{"lat":38.2489,"lng":-112.3403,"tier":"good","sat":"G19","age_sec":464,"frp":144.2,"tempK":424.6},{"lat":38.3187,"lng":-112.5893,"tier":"good","sat":"G19","age_sec":464,"frp":143.0,"tempK":600.4},{"lat":37.4688,"lng":-114.2066,"tier":"high","sat":"G18","age_sec":459,"frp":139.0},{"lat":37.4447,"lng":-114.1626,"tier":"good","sat":"G18","age_sec":459,"frp":121.1,"tempK":757.6},{"lat":37.4195,"lng":-114.1455,"tier":"medium","sat":"G18","age_sec":459,"frp":120.1},{"lat":39.9153,"lng":-112.2908,"tier":"good","sat":"G19","age_sec":464,"frp":118.3,"tempK":476.5},{"lat":38.2621,"lng":-112.3008,"tier":"good","sat":"G18","age_sec":459,"frp":113.8,"tempK":471.8},{"lat":18.2533,"lng":-71.6174,"tier":"high","sat":"G19","age_sec":464,"frp":113.3},{"lat":39.9024,"lng":-112.2557,"tier":"good","sat":"G18","age_sec":459,"frp":86.3,"tempK":520.0},{"lat":18.618,"lng":-69.3324,"tier":"good","sat":"G19","age_sec":464,"frp":53.9,"tempK":551.3},{"lat":35.7565,"lng":-101.2027,"tier":"good","sat":"G19","age_sec":464,"frp":53.4,"tempK":402.4},{"lat":30.4827,"lng":-93.6773,"tier":"good","sat":"G19","age_sec":464,"frp":53.2,"tempK":500.3},{"lat":17.8946,"lng":-93.1848,"tier":"good","sat":"G19","age_sec":464,"frp":47.3,"tempK":401.4},{"lat":20.0095,"lng":-89.9282,"tier":"good","sat":"G19","age_sec":464,"frp":44.4,"tempK":411.5},{"lat":18.5047,"lng":-96.1494,"tier":"good","sat":"G19","age_sec":464,"frp":28.4,"tempK":517.5}]}