{"generated_at":"2026-07-24T22:03:28Z","newest_granule":"2026-07-24T21:56:17Z","product":"GOES-R ABI L2 FDC (Fire/Hot Spot Characterization), CONUS sector, 2km","counts":{"total":201,"g19":83,"g18":142},"detections":[{"lat":51.4504,"lng":-122.4388,"tier":"high","sat":"G19","age_sec":431,"frp":5612.3},{"lat":44.4806,"lng":-119.8847,"tier":"good","sat":"G19","age_sec":431,"frp":4037.7,"tempK":850.9},{"lat":51.1771,"lng":-122.9354,"tier":"high","sat":"G19","age_sec":431,"frp":3966.4},{"lat":51.0379,"lng":-121.6323,"tier":"good","sat":"G18","age_sec":431,"frp":3158.7,"tempK":2056.9},{"lat":51.2952,"lng":-121.9884,"tier":"good","sat":"G19","age_sec":431,"frp":2897.2,"tempK":2763.6},{"lat":51.1275,"lng":-122.8038,"tier":"high","sat":"G19","age_sec":431,"frp":2834.3},{"lat":51.0145,"lng":-121.7067,"tier":"good","sat":"G19","age_sec":431,"frp":2768.3,"tempK":1724.1},{"lat":44.4848,"lng":-119.9324,"tier":"good","sat":"G19","age_sec":431,"frp":2509.6,"tempK":1301.1},{"lat":51.2459,"lng":-121.8607,"tier":"good","sat":"G19","age_sec":431,"frp":2406.8,"tempK":1082.7},{"lat":51.2334,"lng":-121.74,"tier":"high","sat":"G19","age_sec":431,"frp":2341.0},{"lat":48.0187,"lng":-120.7866,"tier":"good","sat":"G18","age_sec":431,"frp":2165.1,"tempK":666.8},{"lat":44.4524,"lng":-119.8517,"tier":"good","sat":"G18","age_sec":431,"frp":1925.2,"tempK":882.3},{"lat":48.0528,"lng":-120.7742,"tier":"good","sat":"G18","age_sec":431,"frp":1806.9,"tempK":2901.3},{"lat":51.0083,"lng":-121.6469,"tier":"high","sat":"G19","age_sec":431,"frp":1504.4},{"lat":48.0024,"lng":-120.7721,"tier":"good","sat":"G19","age_sec":431,"frp":1483.0,"tempK":1267.9},{"lat":50.9992,"lng":-121.6791,"tier":"good","sat":"G18","age_sec":431,"frp":1448.7,"tempK":2307.0},{"lat":51.0205,"lng":-121.7664,"tier":"high","sat":"G19","age_sec":431,"frp":1429.8},{"lat":48.978,"lng":-120.6139,"tier":"good","sat":"G18","age_sec":431,"frp":1390.3,"tempK":638.0},{"lat":48.9443,"lng":-120.5958,"tier":"good","sat":"G18","age_sec":431,"frp":1383.4,"tempK":622.5},{"lat":44.5356,"lng":-120.5085,"tier":"good","sat":"G19","age_sec":431,"frp":1129.1,"tempK":1657.4},{"lat":44.451,"lng":-119.8931,"tier":"high","sat":"G19","age_sec":431,"frp":1044.4},{"lat":51.1836,"lng":-122.998,"tier":"high","sat":"G19","age_sec":431,"frp":1042.0},{"lat":31.1923,"lng":-115.704,"tier":"good","sat":"G19","age_sec":431,"frp":1025.9,"tempK":768.8},{"lat":44.5207,"lng":-120.4518,"tier":"good","sat":"G18","age_sec":431,"frp":987.4,"tempK":1700.0},{"lat":47.9532,"lng":-120.7499,"tier":"good","sat":"G18","age_sec":431,"frp":887.2,"tempK":1065.9},{"lat":51.1908,"lng":-121.6743,"tier":"high","sat":"G19","age_sec":431,"frp":880.1},{"lat":44.4844,"lng":-119.8123,"tier":"high","sat":"G18","age_sec":431,"frp":870.0},{"lat":43.0156,"lng":-118.4421,"tier":"good","sat":"G18","age_sec":431,"frp":834.5,"tempK":654.6},{"lat":48.943,"lng":-120.6272,"tier":"good","sat":"G18","age_sec":431,"frp":798.8,"tempK":608.4},{"lat":47.9697,"lng":-120.7745,"tier":"good","sat":"G19","age_sec":431,"frp":789.9,"tempK":633.3},{"lat":47.952,"lng":-120.7805,"tier":"good","sat":"G18","age_sec":431,"frp":778.7,"tempK":701.4},{"lat":49.0014,"lng":-120.7291,"tier":"good","sat":"G19","age_sec":431,"frp":748.2,"tempK":583.1},{"lat":44.4535,"lng":-119.8229,"tier":"high","sat":"G18","age_sec":431,"frp":743.2},{"lat":51.0674,"lng":-122.915,"tier":"good","sat":"G19","age_sec":431,"frp":716.1,"tempK":771.9},{"lat":51.4938,"lng":-122.5082,"tier":"high","sat":"G19","age_sec":431,"frp":714.7},{"lat":44.513,"lng":-119.8592,"tier":"good","sat":"G18","age_sec":431,"frp":693.8,"tempK":740.2},{"lat":43.1296,"lng":-122.5631,"tier":"good","sat":"G18","age_sec":431,"frp":684.9,"tempK":590.9},{"lat":43.1441,"lng":-118.8991,"tier":"good","sat":"G18","age_sec":431,"frp":625.2,"tempK":646.0},{"lat":51.0934,"lng":-121.7773,"tier":"high","sat":"G19","age_sec":431,"frp":614.3},{"lat":51.0738,"lng":-122.9773,"tier":"high","sat":"G19","age_sec":431,"frp":598.4},{"lat":48.2577,"lng":-119.1063,"tier":"good","sat":"G18","age_sec":431,"frp":578.0,"tempK":666.3},{"lat":43.1472,"lng":-118.9371,"tier":"good","sat":"G19","age_sec":431,"frp":576.5,"tempK":787.5},{"lat":43.0208,"lng":-118.4781,"tier":"high","sat":"G19","age_sec":431,"frp":557.8},{"lat":43.2038,"lng":-118.8782,"tier":"good","sat":"G18","age_sec":431,"frp":555.0,"tempK":776.5},{"lat":43.1757,"lng":-118.9269,"tier":"good","sat":"G19","age_sec":431,"frp":554.0,"tempK":513.6},{"lat":51.0266,"lng":-121.8262,"tier":"good","sat":"G19","age_sec":431,"frp":550.3,"tempK":903.5},{"lat":43.0245,"lng":-118.5224,"tier":"high","sat":"G19","age_sec":431,"frp":549.9},{"lat":31.1943,"lng":-115.7377,"tier":"high","sat":"G19","age_sec":431,"frp":536.6},{"lat":48.2563,"lng":-119.1377,"tier":"good","sat":"G18","age_sec":431,"frp":531.3,"tempK":588.4},{"lat":44.5185,"lng":-119.9716,"tier":"good","sat":"G19","age_sec":431,"frp":513.6,"tempK":594.8},{"lat":51.2827,"lng":-121.867,"tier":"high","sat":"G19","age_sec":431,"frp":501.6},{"lat":44.5196,"lng":-120.4804,"tier":"good","sat":"G18","age_sec":431,"frp":491.0,"tempK":1094.1},{"lat":43.2042,"lng":-118.9166,"tier":"good","sat":"G19","age_sec":431,"frp":486.1,"tempK":894.6},{"lat":43.1406,"lng":-122.5962,"tier":"good","sat":"G19","age_sec":431,"frp":474.6,"tempK":535.3},{"lat":43.2005,"lng":-118.8718,"tier":"high","sat":"G19","age_sec":431,"frp":470.4},{"lat":48.2233,"lng":-119.1203,"tier":"good","sat":"G18","age_sec":431,"frp":454.4,"tempK":506.7},{"lat":43.174,"lng":-118.8886,"tier":"good","sat":"G18","age_sec":431,"frp":453.9,"tempK":548.3},{"lat":49.8203,"lng":-121.389,"tier":"good","sat":"G18","age_sec":431,"frp":442.8,"tempK":552.9},{"lat":49.819,"lng":-121.4208,"tier":"good","sat":"G18","age_sec":431,"frp":438.4,"tempK":539.4},{"lat":43.2365,"lng":-118.9514,"tier":"good","sat":"G19","age_sec":431,"frp":423.7,"tempK":933.2},{"lat":51.197,"lng":-121.7345,"tier":"high","sat":"G19","age_sec":431,"frp":415.1},{"lat":48.0175,"lng":-120.8173,"tier":"good","sat":"G18","age_sec":431,"frp":413.7,"tempK":577.0},{"lat":43.1452,"lng":-118.8708,"tier":"good","sat":"G18","age_sec":431,"frp":412.6,"tempK":659.2},{"lat":45.0041,"lng":-120.6367,"tier":"good","sat":"G19","age_sec":431,"frp":410.4,"tempK":604.1},{"lat":43.1751,"lng":-118.8603,"tier":"high","sat":"G18","age_sec":431,"frp":384.4},{"lat":43.2337,"lng":-118.8677,"tier":"high","sat":"G18","age_sec":431,"frp":374.6},{"lat":51.2094,"lng":-121.8551,"tier":"high","sat":"G19","age_sec":431,"frp":372.0},{"lat":48.0515,"lng":-120.8049,"tier":"high","sat":"G18","age_sec":431,"frp":368.5},{"lat":48.9456,"lng":-120.5643,"tier":"good","sat":"G18","age_sec":431,"frp":360.9,"tempK":542.8},{"lat":49.8216,"lng":-121.3571,"tier":"good","sat":"G18","age_sec":431,"frp":360.2,"tempK":653.3},{"lat":51.0392,"lng":-121.5995,"tier":"high","sat":"G18","age_sec":431,"frp":356.4},{"lat":44.5056,"lng":-120.8521,"tier":"high","sat":"G18","age_sec":431,"frp":348.0},{"lat":44.5088,"lng":-120.7664,"tier":"high","sat":"G18","age_sec":431,"frp":344.4},{"lat":44.478,"lng":-120.7764,"tier":"good","sat":"G18","age_sec":431,"frp":343.7,"tempK":744.7},{"lat":49.8284,"lng":-121.472,"tier":"good","sat":"G19","age_sec":431,"frp":342.8,"tempK":497.8},{"lat":48.2443,"lng":-119.1269,"tier":"high","sat":"G19","age_sec":431,"frp":332.8},{"lat":50.9952,"lng":-121.7772,"tier":"good","sat":"G18","age_sec":431,"frp":323.7,"tempK":877.0},{"lat":44.6443,"lng":-121.3857,"tier":"good","sat":"G19","age_sec":431,"frp":317.2,"tempK":976.6},{"lat":43.208,"lng":-118.9617,"tier":"good","sat":"G19","age_sec":431,"frp":309.4,"tempK":492.5},{"lat":47.9508,"lng":-120.8112,"tier":"good","sat":"G18","age_sec":431,"frp":304.2,"tempK":749.6},{"lat":42.6267,"lng":-117.2706,"tier":"good","sat":"G18","age_sec":431,"frp":301.8,"tempK":505.6},{"lat":43.1795,"lng":-118.9718,"tier":"good","sat":"G19","age_sec":431,"frp":297.7,"tempK":514.4},{"lat":48.2219,"lng":-119.1516,"tier":"good","sat":"G18","age_sec":431,"frp":296.8,"tempK":451.0},{"lat":43.1593,"lng":-122.555,"tier":"good","sat":"G18","age_sec":431,"frp":290.5,"tempK":615.0},{"lat":31.1903,"lng":-115.6703,"tier":"good","sat":"G19","age_sec":431,"frp":287.5,"tempK":473.6},{"lat":42.4153,"lng":-116.7651,"tier":"good","sat":"G19","age_sec":431,"frp":286.5,"tempK":463.8},{"lat":42.6279,"lng":-117.2421,"tier":"good","sat":"G18","age_sec":431,"frp":283.8,"tempK":969.4},{"lat":45.0384,"lng":-120.6784,"tier":"good","sat":"G19","age_sec":431,"frp":275.1,"tempK":769.7},{"lat":49.0131,"lng":-120.6006,"tier":"good","sat":"G18","age_sec":431,"frp":274.0,"tempK":478.2},{"lat":48.9093,"lng":-120.609,"tier":"good","sat":"G18","age_sec":431,"frp":259.5,"tempK":602.5},{"lat":44.0111,"lng":-120.0228,"tier":"good","sat":"G19","age_sec":431,"frp":257.0,"tempK":442.3},{"lat":44.4749,"lng":-120.862,"tier":"high","sat":"G18","age_sec":431,"frp":256.8},{"lat":44.0695,"lng":-120.0051,"tier":"good","sat":"G19","age_sec":431,"frp":254.1,"tempK":560.5},{"lat":31.1678,"lng":-115.6884,"tier":"high","sat":"G19","age_sec":431,"frp":252.2},{"lat":44.5217,"lng":-120.4232,"tier":"high","sat":"G18","age_sec":431,"frp":251.0},{"lat":45.2815,"lng":-121.5107,"tier":"good","sat":"G18","age_sec":431,"frp":250.7,"tempK":907.9},{"lat":44.0234,"lng":-119.9976,"tier":"good","sat":"G18","age_sec":431,"frp":249.3,"tempK":577.3},{"lat":44.6068,"lng":-120.5931,"tier":"good","sat":"G18","age_sec":431,"frp":245.8,"tempK":519.2},{"lat":43.2911,"lng":-118.1983,"tier":"good","sat":"G19","age_sec":431,"frp":245.2,"tempK":800.5},{"lat":44.6079,"lng":-120.5644,"tier":"good","sat":"G18","age_sec":431,"frp":243.5,"tempK":879.7},{"lat":43.3226,"lng":-117.8702,"tier":"good","sat":"G19","age_sec":431,"frp":233.0,"tempK":522.2},{"lat":43.0168,"lng":-118.4138,"tier":"high","sat":"G18","age_sec":431,"frp":223.8},{"lat":48.9767,"lng":-120.6454,"tier":"good","sat":"G18","age_sec":431,"frp":212.6,"tempK":475.7},{"lat":43.1008,"lng":-122.5439,"tier":"good","sat":"G18","age_sec":431,"frp":205.7,"tempK":589.1},{"lat":49.8512,"lng":-121.5031,"tier":"good","sat":"G18","age_sec":431,"frp":205.3,"tempK":469.4},{"lat":45.2511,"lng":-121.4918,"tier":"high","sat":"G18","age_sec":431,"frp":205.2},{"lat":43.2404,"lng":-118.9965,"tier":"good","sat":"G19","age_sec":431,"frp":196.5,"tempK":509.9},{"lat":43.2326,"lng":-118.8961,"tier":"good","sat":"G18","age_sec":431,"frp":194.8,"tempK":789.6},{"lat":43.2928,"lng":-118.1455,"tier":"good","sat":"G18","age_sec":431,"frp":191.7,"tempK":712.8},{"lat":43.0999,"lng":-122.5713,"tier":"good","sat":"G18","age_sec":431,"frp":191.0,"tempK":581.1},{"lat":47.9884,"lng":-120.7068,"tier":"high","sat":"G18","age_sec":431,"frp":190.4},{"lat":43.2315,"lng":-118.9244,"tier":"good","sat":"G18","age_sec":431,"frp":184.7,"tempK":617.0},{"lat":42.9859,"lng":-118.4527,"tier":"good","sat":"G18","age_sec":431,"frp":182.2,"tempK":652.5},{"lat":44.4791,"lng":-120.7479,"tier":"high","sat":"G18","age_sec":431,"frp":178.2},{"lat":43.9939,"lng":-119.9794,"tier":"good","sat":"G18","age_sec":431,"frp":176.1,"tempK":537.1},{"lat":45.478,"lng":-121.2476,"tier":"good","sat":"G18","age_sec":431,"frp":172.9,"tempK":485.6},{"lat":37.7081,"lng":-113.3134,"tier":"good","sat":"G19","age_sec":431,"frp":169.3,"tempK":499.9},{"lat":42.5406,"lng":-117.2471,"tier":"good","sat":"G18","age_sec":431,"frp":168.3,"tempK":556.1},{"lat":48.3032,"lng":-118.8407,"tier":"good","sat":"G18","age_sec":431,"frp":167.1,"tempK":612.5},{"lat":43.3263,"lng":-117.914,"tier":"good","sat":"G19","age_sec":431,"frp":162.9,"tempK":449.9},{"lat":44.5067,"lng":-120.8235,"tier":"medium","sat":"G18","age_sec":431,"frp":161.6},{"lat":45.25,"lng":-121.5206,"tier":"high","sat":"G18","age_sec":431,"frp":160.0},{"lat":44.0549,"lng":-119.9588,"tier":"high","sat":"G18","age_sec":431,"frp":159.6},{"lat":44.4759,"lng":-120.8335,"tier":"medium","sat":"G18","age_sec":431,"frp":157.9},{"lat":17.8343,"lng":-93.1151,"tier":"good","sat":"G19","age_sec":431,"frp":156.9,"tempK":866.2},{"lat":44.0245,"lng":-119.9691,"tier":"good","sat":"G18","age_sec":431,"frp":156.6,"tempK":589.4},{"lat":43.306,"lng":-117.8306,"tier":"good","sat":"G18","age_sec":431,"frp":153.7,"tempK":517.9},{"lat":31.2187,"lng":-115.7533,"tier":"medium","sat":"G19","age_sec":431,"frp":145.1},{"lat":37.5216,"lng":-120.3755,"tier":"medium","sat":"G18","age_sec":431,"frp":144.8},{"lat":43.3048,"lng":-117.8592,"tier":"good","sat":"G18","age_sec":431,"frp":141.7,"tempK":468.1},{"lat":44.4809,"lng":-119.8986,"tier":"medium","sat":"G18","age_sec":431,"frp":139.1},{"lat":48.9106,"lng":-120.5776,"tier":"good","sat":"G18","age_sec":431,"frp":133.6,"tempK":442.1},{"lat":44.0538,"lng":-119.9873,"tier":"good","sat":"G18","age_sec":431,"frp":130.7,"tempK":524.3},{"lat":43.2904,"lng":-117.8368,"tier":"good","sat":"G19","age_sec":431,"frp":130.6,"tempK":444.9},{"lat":43.9929,"lng":-120.0078,"tier":"good","sat":"G18","age_sec":431,"frp":123.1,"tempK":673.1},{"lat":43.336,"lng":-117.8194,"tier":"good","sat":"G18","age_sec":431,"frp":120.9,"tempK":531.8},{"lat":42.655,"lng":-117.2878,"tier":"good","sat":"G18","age_sec":431,"frp":115.6,"tempK":484.4},{"lat":42.5689,"lng":-117.2643,"tier":"good","sat":"G18","age_sec":431,"frp":109.1,"tempK":499.8},{"lat":46.113,"lng":-115.1792,"tier":"good","sat":"G19","age_sec":431,"frp":108.7,"tempK":539.7},{"lat":42.5394,"lng":-117.2755,"tier":"good","sat":"G18","age_sec":431,"frp":107.6,"tempK":441.5},{"lat":46.1094,"lng":-115.1359,"tier":"good","sat":"G19","age_sec":431,"frp":107.2,"tempK":431.5},{"lat":26.2508,"lng":-111.5209,"tier":"medium","sat":"G19","age_sec":431,"frp":106.7},{"lat":48.1686,"lng":-118.8347,"tier":"good","sat":"G18","age_sec":431,"frp":106.3,"tempK":413.3},{"lat":45.4822,"lng":-120.4739,"tier":"good","sat":"G19","age_sec":431,"frp":104.0,"tempK":447.4},{"lat":44.132,"lng":-120.3766,"tier":"good","sat":"G19","age_sec":431,"frp":98.0,"tempK":461.3},{"lat":46.9703,"lng":-114.2996,"tier":"good","sat":"G18","age_sec":431,"frp":95.1,"tempK":542.1},{"lat":26.2522,"lng":-111.5499,"tier":"good","sat":"G19","age_sec":431,"frp":89.3,"tempK":400.8},{"lat":32.6723,"lng":-115.6236,"tier":"good","sat":"G18","age_sec":431,"frp":87.5,"tempK":408.6},{"lat":32.6714,"lng":-115.6484,"tier":"good","sat":"G18","age_sec":431,"frp":85.2,"tempK":439.9},{"lat":32.6732,"lng":-115.5989,"tier":"good","sat":"G18","age_sec":431,"frp":83.4,"tempK":429.9},{"lat":26.297,"lng":-111.5699,"tier":"good","sat":"G19","age_sec":431,"frp":81.3,"tempK":424.2},{"lat":46.0926,"lng":-115.1316,"tier":"good","sat":"G18","age_sec":431,"frp":80.3,"tempK":461.9},{"lat":36.6785,"lng":-117.2049,"tier":"good","sat":"G18","age_sec":431,"frp":80.2,"tempK":414.0},{"lat":32.6492,"lng":-115.6059,"tier":"good","sat":"G18","age_sec":431,"frp":79.5,"tempK":405.9},{"lat":17.852,"lng":-94.1345,"tier":"good","sat":"G19","age_sec":431,"frp":79.3,"tempK":478.4},{"lat":26.2285,"lng":-111.5109,"tier":"good","sat":"G19","age_sec":431,"frp":77.2,"tempK":403.8},{"lat":17.854,"lng":-93.1176,"tier":"good","sat":"G19","age_sec":431,"frp":77.0,"tempK":560.9},{"lat":31.8357,"lng":-113.3164,"tier":"good","sat":"G18","age_sec":431,"frp":76.2,"tempK":407.4},{"lat":31.812,"lng":-113.324,"tier":"good","sat":"G18","age_sec":431,"frp":76.2,"tempK":405.1},{"lat":26.2746,"lng":-111.5599,"tier":"good","sat":"G19","age_sec":431,"frp":74.7,"tempK":422.5},{"lat":26.2298,"lng":-111.5399,"tier":"good","sat":"G19","age_sec":431,"frp":74.2,"tempK":408.8},{"lat":26.2877,"lng":-111.5078,"tier":"good","sat":"G18","age_sec":431,"frp":72.3,"tempK":421.4},{"lat":26.308,"lng":-111.5499,"tier":"good","sat":"G18","age_sec":431,"frp":70.0,"tempK":427.4},{"lat":36.6853,"lng":-117.0243,"tier":"good","sat":"G18","age_sec":431,"frp":65.9,"tempK":565.0},{"lat":31.811,"lng":-113.3491,"tier":"good","sat":"G18","age_sec":431,"frp":63.8,"tempK":408.4},{"lat":36.7102,"lng":-117.042,"tier":"good","sat":"G18","age_sec":431,"frp":63.6,"tempK":503.9},{"lat":31.8596,"lng":-113.3087,"tier":"good","sat":"G18","age_sec":431,"frp":55.6,"tempK":409.2},{"lat":31.8567,"lng":-113.3841,"tier":"good","sat":"G18","age_sec":431,"frp":55.2,"tempK":403.9},{"lat":31.8805,"lng":-113.3765,"tier":"good","sat":"G18","age_sec":431,"frp":54.3,"tempK":406.0},{"lat":27.1329,"lng":-109.6108,"tier":"good","sat":"G19","age_sec":431,"frp":50.7,"tempK":540.7},{"lat":41.5161,"lng":-113.946,"tier":"good","sat":"G18","age_sec":431,"frp":49.9,"tempK":786.6},{"lat":17.8715,"lng":-89.0745,"tier":"good","sat":"G19","age_sec":431,"frp":48.0,"tempK":519.3},{"lat":27.1316,"lng":-109.5826,"tier":"good","sat":"G19","age_sec":431,"frp":47.5,"tempK":536.7},{"lat":17.9884,"lng":-94.0277,"tier":"good","sat":"G19","age_sec":431,"frp":45.5,"tempK":614.4},{"lat":31.8795,"lng":-113.4017,"tier":"good","sat":"G18","age_sec":431,"frp":45.1,"tempK":413.8},{"lat":31.8367,"lng":-113.2912,"tier":"good","sat":"G18","age_sec":431,"frp":44.8,"tempK":419.3},{"lat":31.6932,"lng":-113.3619,"tier":"good","sat":"G18","age_sec":431,"frp":43.5,"tempK":456.0},{"lat":31.717,"lng":-113.3543,"tier":"good","sat":"G18","age_sec":431,"frp":42.8,"tempK":451.8},{"lat":32.4407,"lng":-113.5445,"tier":"good","sat":"G18","age_sec":431,"frp":41.8,"tempK":401.2},{"lat":32.7247,"lng":-114.2009,"tier":"good","sat":"G18","age_sec":431,"frp":41.6,"tempK":419.4},{"lat":17.8946,"lng":-93.1848,"tier":"good","sat":"G19","age_sec":431,"frp":40.8,"tempK":419.5},{"lat":32.3246,"lng":-113.4823,"tier":"good","sat":"G18","age_sec":431,"frp":38.6,"tempK":406.1},{"lat":29.8609,"lng":-93.4881,"tier":"good","sat":"G19","age_sec":431,"frp":38.5,"tempK":528.7},{"lat":32.7237,"lng":-114.2261,"tier":"good","sat":"G18","age_sec":431,"frp":38.1,"tempK":408.2},{"lat":32.4398,"lng":-113.5698,"tier":"good","sat":"G18","age_sec":431,"frp":37.3,"tempK":405.4},{"lat":34.5158,"lng":-114.8017,"tier":"good","sat":"G18","age_sec":431,"frp":36.9,"tempK":439.1},{"lat":31.8785,"lng":-113.4268,"tier":"good","sat":"G18","age_sec":431,"frp":34.3,"tempK":431.8},{"lat":34.8046,"lng":-114.3497,"tier":"good","sat":"G18","age_sec":431,"frp":32.1,"tempK":433.0},{"lat":31.7407,"lng":-113.3468,"tier":"good","sat":"G18","age_sec":431,"frp":32.1,"tempK":456.9},{"lat":32.746,"lng":-114.2688,"tier":"good","sat":"G18","age_sec":431,"frp":30.2,"tempK":406.8},{"lat":18.5553,"lng":-69.9917,"tier":"medium","sat":"G19","age_sec":431,"frp":29.8},{"lat":31.7644,"lng":-113.3392,"tier":"good","sat":"G18","age_sec":431,"frp":28.0,"tempK":425.6},{"lat":31.7397,"lng":-113.3719,"tier":"good","sat":"G18","age_sec":431,"frp":26.7,"tempK":509.7},{"lat":18.3334,"lng":-88.2382,"tier":"good","sat":"G19","age_sec":431,"frp":25.4,"tempK":453.6},{"lat":31.6942,"lng":-113.3368,"tier":"good","sat":"G18","age_sec":431,"frp":25.4,"tempK":574.8},{"lat":17.0709,"lng":-89.3181,"tier":"good","sat":"G19","age_sec":431,"frp":23.3,"tempK":406.2},{"lat":18.6316,"lng":-92.3073,"tier":"good","sat":"G19","age_sec":431,"frp":21.6,"tempK":475.7},{"lat":24.9783,"lng":-111.7868,"tier":"good","sat":"G19","age_sec":431,"frp":20.9,"tempK":441.6},{"lat":25.3459,"lng":-111.2682,"tier":"good","sat":"G18","age_sec":431,"frp":20.9,"tempK":411.3},{"lat":25.0394,"lng":-111.4695,"tier":"good","sat":"G18","age_sec":431,"frp":20.5,"tempK":676.3},{"lat":25.3668,"lng":-111.2864,"tier":"good","sat":"G18","age_sec":431,"frp":20.0,"tempK":413.5}]}