{"generated_at":"2026-07-17T01:02:56Z","newest_granule":"2026-07-17T00:56:19Z","product":"GOES-R ABI L2 FDC (Fire/Hot Spot Characterization), CONUS sector, 2km","counts":{"total":72,"g19":12,"g18":61},"detections":[{"lat":48.1033,"lng":-119.0378,"tier":"high","sat":"G19","age_sec":401,"frp":1926.3},{"lat":48.0945,"lng":-118.9882,"tier":"good","sat":"G18","age_sec":397,"frp":1788.7,"tempK":624.2},{"lat":48.0931,"lng":-119.0195,"tier":"good","sat":"G18","age_sec":397,"frp":1746.0,"tempK":744.0},{"lat":45.5145,"lng":-120.2863,"tier":"good","sat":"G18","age_sec":397,"frp":1655.5,"tempK":934.1},{"lat":45.5463,"lng":-120.2753,"tier":"good","sat":"G18","age_sec":397,"frp":1539.7,"tempK":903.4},{"lat":45.5156,"lng":-120.257,"tier":"good","sat":"G18","age_sec":397,"frp":1407.1,"tempK":1114.9},{"lat":45.5474,"lng":-120.246,"tier":"good","sat":"G18","age_sec":397,"frp":1026.2,"tempK":997.5},{"lat":48.1274,"lng":-119.0055,"tier":"good","sat":"G18","age_sec":397,"frp":854.6,"tempK":1311.4},{"lat":48.1287,"lng":-118.9742,"tier":"good","sat":"G18","age_sec":397,"frp":847.7,"tempK":983.2},{"lat":44.0943,"lng":-120.5076,"tier":"good","sat":"G18","age_sec":397,"frp":778.2,"tempK":713.5},{"lat":44.4849,"lng":-121.4213,"tier":"good","sat":"G18","age_sec":397,"frp":764.6,"tempK":729.8},{"lat":44.1249,"lng":-120.4976,"tier":"good","sat":"G18","age_sec":397,"frp":656.6,"tempK":742.0},{"lat":45.5451,"lng":-120.3046,"tier":"good","sat":"G18","age_sec":397,"frp":637.2,"tempK":743.2},{"lat":45.5134,"lng":-120.3155,"tier":"good","sat":"G18","age_sec":397,"frp":584.6,"tempK":768.1},{"lat":46.8907,"lng":-119.3436,"tier":"good","sat":"G18","age_sec":397,"frp":540.7,"tempK":1650.1},{"lat":42.6212,"lng":-122.9159,"tier":"good","sat":"G18","age_sec":397,"frp":526.9,"tempK":614.7},{"lat":48.1361,"lng":-119.0345,"tier":"good","sat":"G19","age_sec":401,"frp":471.3,"tempK":724.9},{"lat":45.6075,"lng":-120.3118,"tier":"good","sat":"G18","age_sec":397,"frp":450.7,"tempK":820.9},{"lat":46.8577,"lng":-119.3563,"tier":"good","sat":"G18","age_sec":397,"frp":438.8,"tempK":568.8},{"lat":44.486,"lng":-121.3929,"tier":"good","sat":"G18","age_sec":397,"frp":433.7,"tempK":651.0},{"lat":44.5652,"lng":-120.8892,"tier":"good","sat":"G18","age_sec":397,"frp":418.3,"tempK":657.2},{"lat":46.859,"lng":-119.3259,"tier":"good","sat":"G18","age_sec":397,"frp":418.1,"tempK":552.3},{"lat":46.892,"lng":-119.3132,"tier":"good","sat":"G18","age_sec":397,"frp":417.8,"tempK":634.4},{"lat":44.4839,"lng":-121.4497,"tier":"good","sat":"G18","age_sec":397,"frp":402.7,"tempK":628.3},{"lat":44.5355,"lng":-120.8706,"tier":"good","sat":"G18","age_sec":397,"frp":395.2,"tempK":1114.2},{"lat":48.1301,"lng":-118.9429,"tier":"high","sat":"G18","age_sec":397,"frp":385.7},{"lat":45.544,"lng":-120.3338,"tier":"good","sat":"G18","age_sec":397,"frp":325.4,"tempK":718.6},{"lat":19.406,"lng":-155.2821,"tier":"good","sat":"G18","age_sec":397,"frp":317.6,"tempK":417.6},{"lat":44.8916,"lng":-120.356,"tier":"good","sat":"G18","age_sec":397,"frp":291.6,"tempK":673.7},{"lat":45.1296,"lng":-120.5899,"tier":"good","sat":"G18","age_sec":397,"frp":290.7,"tempK":607.8},{"lat":46.8976,"lng":-119.397,"tier":"good","sat":"G19","age_sec":401,"frp":277.7,"tempK":568.4},{"lat":45.5757,"lng":-120.3229,"tier":"good","sat":"G18","age_sec":397,"frp":258.6,"tempK":648.4},{"lat":45.0982,"lng":-120.6004,"tier":"good","sat":"G18","age_sec":397,"frp":235.3,"tempK":553.5},{"lat":44.8005,"lng":-120.3298,"tier":"good","sat":"G18","age_sec":397,"frp":231.1,"tempK":602.2},{"lat":45.6086,"lng":-120.2825,"tier":"good","sat":"G18","age_sec":397,"frp":221.3,"tempK":596.0},{"lat":44.8371,"lng":-120.1749,"tier":"good","sat":"G18","age_sec":397,"frp":221.3,"tempK":570.6},{"lat":44.8072,"lng":-120.1566,"tier":"good","sat":"G18","age_sec":397,"frp":219.2,"tempK":548.4},{"lat":45.5768,"lng":-120.2936,"tier":"good","sat":"G18","age_sec":397,"frp":209.8,"tempK":603.4},{"lat":45.6063,"lng":-120.3412,"tier":"good","sat":"G18","age_sec":397,"frp":204.1,"tempK":719.7},{"lat":45.5779,"lng":-120.2643,"tier":"good","sat":"G18","age_sec":397,"frp":186.7,"tempK":618.7},{"lat":44.1279,"lng":-119.9874,"tier":"good","sat":"G19","age_sec":401,"frp":186.2,"tempK":484.9},{"lat":19.4261,"lng":-155.2849,"tier":"good","sat":"G18","age_sec":397,"frp":183.4,"tempK":464.3},{"lat":44.9217,"lng":-120.3743,"tier":"good","sat":"G18","age_sec":397,"frp":181.6,"tempK":520.4},{"lat":43.745,"lng":-119.4461,"tier":"good","sat":"G18","age_sec":397,"frp":174.6,"tempK":660.0},{"lat":46.6025,"lng":-118.53,"tier":"good","sat":"G18","age_sec":397,"frp":173.3,"tempK":508.6},{"lat":45.1698,"lng":-120.3472,"tier":"good","sat":"G18","age_sec":397,"frp":171.2,"tempK":589.1},{"lat":39.7353,"lng":-120.12,"tier":"high","sat":"G18","age_sec":397,"frp":169.9},{"lat":44.8731,"lng":-120.8458,"tier":"good","sat":"G18","age_sec":397,"frp":169.3,"tempK":807.2},{"lat":40.9471,"lng":-121.0858,"tier":"good","sat":"G19","age_sec":401,"frp":166.8,"tempK":628.2},{"lat":46.5697,"lng":-118.5431,"tier":"good","sat":"G18","age_sec":397,"frp":165.8,"tempK":684.2},{"lat":44.5951,"lng":-120.9078,"tier":"good","sat":"G18","age_sec":397,"frp":162.3,"tempK":556.0},{"lat":44.1238,"lng":-120.526,"tier":"high","sat":"G18","age_sec":397,"frp":157.6},{"lat":39.7359,"lng":-120.1424,"tier":"good","sat":"G19","age_sec":401,"frp":157.1,"tempK":507.6},{"lat":45.2013,"lng":-120.3365,"tier":"good","sat":"G18","age_sec":397,"frp":154.9,"tempK":581.5},{"lat":19.4064,"lng":-155.303,"tier":"good","sat":"G18","age_sec":397,"frp":147.8,"tempK":405.4},{"lat":46.6038,"lng":-118.4995,"tier":"good","sat":"G18","age_sec":397,"frp":144.5,"tempK":548.1},{"lat":46.6475,"lng":-118.2423,"tier":"good","sat":"G18","age_sec":397,"frp":132.6,"tempK":480.5},{"lat":44.0933,"lng":-120.536,"tier":"high","sat":"G18","age_sec":397,"frp":126.0},{"lat":39.7344,"lng":-120.1463,"tier":"good","sat":"G18","age_sec":397,"frp":119.8,"tempK":557.2},{"lat":44.0649,"lng":-120.4891,"tier":"high","sat":"G18","age_sec":397,"frp":118.8},{"lat":45.3306,"lng":-120.2058,"tier":"good","sat":"G18","age_sec":397,"frp":115.4,"tempK":619.4},{"lat":40.9446,"lng":-121.0319,"tier":"good","sat":"G18","age_sec":397,"frp":114.2,"tempK":503.5},{"lat":43.7551,"lng":-119.4798,"tier":"good","sat":"G19","age_sec":401,"frp":109.5,"tempK":477.2},{"lat":19.3859,"lng":-155.2793,"tier":"medium","sat":"G18","age_sec":397,"frp":106.7},{"lat":43.7591,"lng":-119.5259,"tier":"good","sat":"G19","age_sec":401,"frp":105.2,"tempK":565.2},{"lat":19.4264,"lng":-155.3059,"tier":"medium","sat":"G18","age_sec":397,"frp":98.9},{"lat":52.0228,"lng":-116.8291,"tier":"medium","sat":"G19","age_sec":401,"frp":90.1},{"lat":49.5079,"lng":-118.1747,"tier":"medium","sat":"G19","age_sec":401,"frp":85.2},{"lat":42.6472,"lng":-123.0165,"tier":"good","sat":"G18","age_sec":397,"frp":84.9,"tempK":477.0},{"lat":44.1522,"lng":-120.5729,"tier":"good","sat":"G18","age_sec":397,"frp":77.5,"tempK":539.3},{"lat":44.8146,"lng":-118.4616,"tier":"good","sat":"G18","age_sec":397,"frp":71.0,"tempK":461.0},{"lat":18.1707,"lng":-76.8089,"tier":"good","sat":"G19","age_sec":401,"frp":20.8,"tempK":485.6}]}