{"generated_at":"2026-06-30T17:27:45Z","newest_granule":"2026-06-30T17:21:23Z","product":"GOES-R ABI L2 FDC (Fire/Hot Spot Characterization), CONUS sector, 2km","counts":{"total":55,"g19":33,"g18":31},"detections":[{"lat":37.9149,"lng":-109.7353,"tier":"good","sat":"G18","age_sec":382,"frp":2854.5,"tempK":1060.7},{"lat":37.8982,"lng":-109.7832,"tier":"good","sat":"G19","age_sec":388,"frp":2221.1,"tempK":941.7},{"lat":37.888,"lng":-109.7479,"tier":"good","sat":"G18","age_sec":382,"frp":1144.2,"tempK":2556.1},{"lat":37.9134,"lng":-109.7641,"tier":"high","sat":"G18","age_sec":382,"frp":1010.3},{"lat":37.9164,"lng":-109.7065,"tier":"good","sat":"G18","age_sec":382,"frp":685.2,"tempK":838.1},{"lat":37.9003,"lng":-109.8159,"tier":"high","sat":"G19","age_sec":388,"frp":642.5},{"lat":37.8895,"lng":-109.719,"tier":"good","sat":"G18","age_sec":382,"frp":495.4,"tempK":685.4},{"lat":42.7796,"lng":-103.6028,"tier":"high","sat":"G18","age_sec":382,"frp":359.7},{"lat":37.8415,"lng":-109.7156,"tier":"good","sat":"G19","age_sec":388,"frp":355.9,"tempK":1174.8},{"lat":37.8671,"lng":-109.6452,"tier":"good","sat":"G18","age_sec":382,"frp":355.8,"tempK":662.3},{"lat":37.8667,"lng":-109.7003,"tier":"high","sat":"G19","age_sec":388,"frp":350.2},{"lat":38.0429,"lng":-105.1401,"tier":"high","sat":"G19","age_sec":388,"frp":319.4},{"lat":37.7269,"lng":-108.7118,"tier":"high","sat":"G19","age_sec":388,"frp":302.9},{"lat":37.8709,"lng":-109.7657,"tier":"good","sat":"G19","age_sec":388,"frp":294.3,"tempK":1571.2},{"lat":42.7951,"lng":-103.6402,"tier":"high","sat":"G19","age_sec":388,"frp":291.6},{"lat":37.8402,"lng":-109.6578,"tier":"good","sat":"G18","age_sec":382,"frp":290.0,"tempK":599.6},{"lat":42.7649,"lng":-103.6226,"tier":"high","sat":"G19","age_sec":388,"frp":279.4},{"lat":37.9404,"lng":-109.7515,"tier":"high","sat":"G18","age_sec":382,"frp":265.7},{"lat":42.7669,"lng":-103.6548,"tier":"good","sat":"G19","age_sec":388,"frp":254.5,"tempK":1240.0},{"lat":37.8851,"lng":-109.8054,"tier":"good","sat":"G18","age_sec":382,"frp":247.6,"tempK":804.3},{"lat":37.735,"lng":-108.6618,"tier":"high","sat":"G18","age_sec":382,"frp":245.2},{"lat":37.7334,"lng":-108.691,"tier":"high","sat":"G18","age_sec":382,"frp":219.5},{"lat":37.8656,"lng":-109.674,"tier":"good","sat":"G18","age_sec":382,"frp":200.2,"tempK":1266.5},{"lat":38.0416,"lng":-105.0501,"tier":"high","sat":"G18","age_sec":382,"frp":198.8},{"lat":37.8388,"lng":-109.6866,"tier":"good","sat":"G18","age_sec":382,"frp":197.9,"tempK":484.2},{"lat":37.7366,"lng":-108.6326,"tier":"good","sat":"G18","age_sec":382,"frp":194.3,"tempK":548.2},{"lat":35.0549,"lng":-111.8414,"tier":"high","sat":"G19","age_sec":388,"frp":193.9},{"lat":35.057,"lng":-111.8741,"tier":"high","sat":"G19","age_sec":388,"frp":192.9},{"lat":35.0598,"lng":-111.8218,"tier":"high","sat":"G18","age_sec":382,"frp":192.9},{"lat":37.8435,"lng":-109.7483,"tier":"good","sat":"G19","age_sec":388,"frp":191.4,"tempK":530.5},{"lat":42.7971,"lng":-103.6724,"tier":"high","sat":"G19","age_sec":388,"frp":183.2},{"lat":37.877,"lng":-109.864,"tier":"high","sat":"G19","age_sec":388,"frp":181.7},{"lat":17.8343,"lng":-93.1151,"tier":"good","sat":"G19","age_sec":388,"frp":173.7,"tempK":884.7},{"lat":37.7619,"lng":-108.6487,"tier":"good","sat":"G18","age_sec":382,"frp":171.1,"tempK":706.7},{"lat":37.7603,"lng":-108.6779,"tier":"high","sat":"G18","age_sec":382,"frp":170.6},{"lat":42.8103,"lng":-103.581,"tier":"high","sat":"G18","age_sec":382,"frp":163.4},{"lat":19.406,"lng":-155.2821,"tier":"high","sat":"G18","age_sec":382,"frp":151.6},{"lat":37.912,"lng":-109.7929,"tier":"high","sat":"G18","age_sec":382,"frp":146.7},{"lat":37.8939,"lng":-109.6326,"tier":"good","sat":"G18","age_sec":382,"frp":140.3,"tempK":897.0},{"lat":35.2202,"lng":-79.0815,"tier":"good","sat":"G19","age_sec":388,"frp":134.6,"tempK":677.0},{"lat":37.9434,"lng":-109.6938,"tier":"high","sat":"G18","age_sec":382,"frp":128.2},{"lat":32.1008,"lng":-110.8277,"tier":"good","sat":"G18","age_sec":382,"frp":104.7,"tempK":870.5},{"lat":32.1019,"lng":-110.8016,"tier":"good","sat":"G18","age_sec":382,"frp":99.4,"tempK":723.2},{"lat":17.854,"lng":-93.1176,"tier":"good","sat":"G19","age_sec":388,"frp":94.7,"tempK":681.9},{"lat":35.245,"lng":-79.083,"tier":"good","sat":"G19","age_sec":388,"frp":68.7,"tempK":655.7},{"lat":32.1248,"lng":-110.819,"tier":"good","sat":"G18","age_sec":382,"frp":68.6,"tempK":664.5},{"lat":18.6933,"lng":-70.0062,"tier":"good","sat":"G19","age_sec":388,"frp":66.7,"tempK":613.6},{"lat":17.8346,"lng":-93.1358,"tier":"medium","sat":"G19","age_sec":388,"frp":56.5},{"lat":18.0027,"lng":-67.1533,"tier":"good","sat":"G19","age_sec":388,"frp":53.7,"tempK":426.1},{"lat":17.8946,"lng":-93.1848,"tier":"good","sat":"G19","age_sec":388,"frp":45.7,"tempK":452.3},{"lat":35.4694,"lng":-93.4614,"tier":"good","sat":"G19","age_sec":388,"frp":44.8,"tempK":414.8},{"lat":30.9196,"lng":-92.8715,"tier":"good","sat":"G19","age_sec":388,"frp":40.6,"tempK":503.6},{"lat":34.2212,"lng":-95.2076,"tier":"good","sat":"G19","age_sec":388,"frp":31.6,"tempK":763.4},{"lat":18.0719,"lng":-102.4866,"tier":"good","sat":"G19","age_sec":388,"frp":30.1,"tempK":728.9},{"lat":16.6004,"lng":-98.6486,"tier":"good","sat":"G19","age_sec":388,"frp":22.0,"tempK":617.1}]}