{"generated_at":"2026-06-30T12:13:54Z","newest_granule":"2026-06-30T12:06:23Z","product":"GOES-R ABI L2 FDC (Fire/Hot Spot Characterization), CONUS sector, 2km","counts":{"total":13,"g19":7,"g18":6},"detections":[{"lat":37.8851,"lng":-109.8054,"tier":"good","sat":"G18","age_sec":451,"frp":273.7,"tempK":585.8},{"lat":37.9024,"lng":-109.8488,"tier":"good","sat":"G19","age_sec":457,"frp":235.5,"tempK":635.2},{"lat":37.912,"lng":-109.7929,"tier":"good","sat":"G18","age_sec":451,"frp":226.0,"tempK":617.2},{"lat":35.0598,"lng":-111.8218,"tier":"good","sat":"G18","age_sec":451,"frp":217.1,"tempK":537.3},{"lat":17.8343,"lng":-93.1151,"tier":"good","sat":"G19","age_sec":457,"frp":102.4,"tempK":822.2},{"lat":42.7796,"lng":-103.6028,"tier":"high","sat":"G18","age_sec":451,"frp":88.5},{"lat":34.9852,"lng":-111.8243,"tier":"good","sat":"G18","age_sec":451,"frp":79.0,"tempK":492.0},{"lat":34.9811,"lng":-111.8578,"tier":"good","sat":"G19","age_sec":457,"frp":72.4,"tempK":449.2},{"lat":42.7649,"lng":-103.6226,"tier":"good","sat":"G19","age_sec":457,"frp":70.1,"tempK":529.1},{"lat":33.3001,"lng":-108.6928,"tier":"medium","sat":"G19","age_sec":457,"frp":40.9},{"lat":33.2967,"lng":-108.6297,"tier":"high","sat":"G18","age_sec":451,"frp":36.7},{"lat":18.5047,"lng":-96.1494,"tier":"high","sat":"G19","age_sec":457,"frp":33.2},{"lat":17.8946,"lng":-93.1848,"tier":"good","sat":"G19","age_sec":457,"frp":23.6,"tempK":500.9}]}