{"generated_at":"2026-06-13T13:59:27Z","newest_granule":"2026-06-13T13:51:18Z","product":"GOES-R ABI L2 FDC (Fire/Hot Spot Characterization), CONUS sector, 2km","counts":{"total":4,"g19":2,"g18":2},"detections":[{"lat":34.0665,"lng":-108.2731,"tier":"high","sat":"G18","age_sec":489,"frp":48.2},{"lat":33.8272,"lng":-83.5245,"tier":"high","sat":"G19","age_sec":489,"frp":40.3},{"lat":38.0379,"lng":-106.9504,"tier":"medium","sat":"G18","age_sec":489,"frp":39.2},{"lat":18.5047,"lng":-96.1494,"tier":"good","sat":"G19","age_sec":489,"frp":23.7,"tempK":666.6}]}